<?xml version="1.0" encoding="UTF-8" standalone="yes"?>


<item>       
<title>     [COLOR blue] •S2 UPDATE 22-12-2017 [/COLOR]     </title>
<link>http://Ignoreme</link>
<externallink></externallink>
<thumbnail>http://i.cubeupload.com/0hw4LW.png</thumbnail>
<fanart>http://i.imgur.com/cP0kZuH.jpg</fanart>
</item>





<item>       
<title>                         [COLOR lime] BY LOGAN TV:1[/COLOR]     </title>
<link>http://Ignoreme</link>
<externallink></externallink>
<thumbnail>https://i.imgsafe.org/fe957d1165.png</thumbnail>
<fanart>http://i.imgur.com/cP0kZuH.jpg</fanart>
</item>



 
  
  
  
          <item> 
            <title>|IT|RAI.1</title> 
            <link>plugin://plugin.video.f4mTester/?url=http://iptvpro.vision-new.org:8789/live/gowant/faojuy/144.ts&amp;streamtype=TSDOWNLOADER&amp;name=|IT|RAI.1</link> 
        </item> 
          <item> 
            <title>|IT|RAI.2</title> 
            <link>plugin://plugin.video.f4mTester/?url=http://iptvpro.vision-new.org:8789/live/gowant/faojuy/145.ts&amp;streamtype=TSDOWNLOADER&amp;name=|IT|RAI.2</link> 
        </item> 
          <item> 
            <title>|IT|RAI.3</title> 
            <link>plugin://plugin.video.f4mTester/?url=http://iptvpro.vision-new.org:8789/live/gowant/faojuy/146.ts&amp;streamtype=TSDOWNLOADER&amp;name=|IT|RAI.3</link> 
        </item> 
          <item> 
            <title>|IT|RAI.4</title> 
            <link>plugin://plugin.video.f4mTester/?url=http://iptvpro.vision-new.org:8789/live/gowant/faojuy/147.ts&amp;streamtype=TSDOWNLOADER&amp;name=|IT|RAI.4</link> 
        </item> 
          <item> 
            <title>|IT|RAI.5</title> 
            <link>plugin://plugin.video.f4mTester/?url=http://iptvpro.vision-new.org:8789/live/gowant/faojuy/148.ts&amp;streamtype=TSDOWNLOADER&amp;name=|IT|RAI.5</link> 
        </item> 
          <item> 
            <title>|IT|RAI.PREMIUM</title> 
            <link>plugin://plugin.video.f4mTester/?url=http://iptvpro.vision-new.org:8789/live/gowant/faojuy/149.ts&amp;streamtype=TSDOWNLOADER&amp;name=|IT|RAI.PREMIUM</link> 
        </item> 
          <item> 
            <title>|IT|RAI.MOVIE.HD</title> 
            <link>plugin://plugin.video.f4mTester/?url=http://iptvpro.vision-new.org:8789/live/gowant/faojuy/2737.ts&amp;streamtype=TSDOWNLOADER&amp;name=|IT|RAI.MOVIE.HD</link> 
        </item> 
          <item> 
            <title>|IT|RAI.SPORT+</title> 
            <link>plugin://plugin.video.f4mTester/?url=http://iptvpro.vision-new.org:8789/live/gowant/faojuy/1449.ts&amp;streamtype=TSDOWNLOADER&amp;name=|IT|RAI.SPORT+</link> 
        </item> 
          <item> 
            <title>|IT|RAI.GULP</title> 
            <link>plugin://plugin.video.f4mTester/?url=http://iptvpro.vision-new.org:8789/live/gowant/faojuy/151.ts&amp;streamtype=TSDOWNLOADER&amp;name=|IT|RAI.GULP</link> 
        </item> 
          <item> 
            <title>|IT|RAI.YOYO</title> 
            <link>plugin://plugin.video.f4mTester/?url=http://iptvpro.vision-new.org:8789/live/gowant/faojuy/597.ts&amp;streamtype=TSDOWNLOADER&amp;name=|IT|RAI.YOYO</link> 
        </item> 
          <item> 
            <title>|IT|RAI.NEWS.24</title> 
            <link>plugin://plugin.video.f4mTester/?url=http://iptvpro.vision-new.org:8789/live/gowant/faojuy/1581.ts&amp;streamtype=TSDOWNLOADER&amp;name=|IT|RAI.NEWS.24</link> 
        </item> 
          <item> 
            <title>RADIO_MONTECARLO</title> 
            <link>plugin://plugin.video.f4mTester/?url=http://iptvpro.vision-new.org:8789/live/gowant/faojuy/601.ts&amp;streamtype=TSDOWNLOADER&amp;name=RADIO_MONTECARLO</link> 
        </item> 
          <item> 
            <title>RADIO.105</title> 
            <link>plugin://plugin.video.f4mTester/?url=http://iptvpro.vision-new.org:8789/live/gowant/faojuy/600.ts&amp;streamtype=TSDOWNLOADER&amp;name=RADIO.105</link> 
        </item> 
          <item> 
            <title>|IT|*****GENERALISTI*****|IT|</title> 
            <link>plugin://plugin.video.f4mTester/?url=http://iptvpro.vision-new.org:8789/live/gowant/faojuy/1572.ts&amp;streamtype=TSDOWNLOADER&amp;name=|IT|*****GENERALISTI*****|IT|</link> 
        </item> 
          <item> 
            <title>|IT|ITALIA.1</title> 
            <link>plugin://plugin.video.f4mTester/?url=http://iptvpro.vision-new.org:8789/live/gowant/faojuy/789.ts&amp;streamtype=TSDOWNLOADER&amp;name=|IT|ITALIA.1</link> 
        </item> 
          <item> 
            <title>|IT|RETE.4</title> 
            <link>plugin://plugin.video.f4mTester/?url=http://iptvpro.vision-new.org:8789/live/gowant/faojuy/787.ts&amp;streamtype=TSDOWNLOADER&amp;name=|IT|RETE.4</link> 
        </item> 
          <item> 
            <title>|IT|CANALE.5.HD</title> 
            <link>plugin://plugin.video.f4mTester/?url=http://iptvpro.vision-new.org:8789/live/gowant/faojuy/788.ts&amp;streamtype=TSDOWNLOADER&amp;name=|IT|CANALE.5.HD</link> 
        </item> 
          <item> 
            <title>|IT|CANALE.5</title> 
            <link>plugin://plugin.video.f4mTester/?url=http://iptvpro.vision-new.org:8789/live/gowant/faojuy/78.ts&amp;streamtype=TSDOWNLOADER&amp;name=|IT|CANALE.5</link> 
        </item> 
          <item> 
            <title>|IT|LA.5</title> 
            <link>plugin://plugin.video.f4mTester/?url=http://iptvpro.vision-new.org:8789/live/gowant/faojuy/3670.ts&amp;streamtype=TSDOWNLOADER&amp;name=|IT|LA.5</link> 
        </item> 
          <item> 
            <title>|IT|LA.7</title> 
            <link>plugin://plugin.video.f4mTester/?url=http://iptvpro.vision-new.org:8789/live/gowant/faojuy/3664.ts&amp;streamtype=TSDOWNLOADER&amp;name=|IT|LA.7</link> 
        </item> 
          <item> 
            <title>|IT|LA7d</title> 
            <link>plugin://plugin.video.f4mTester/?url=http://iptvpro.vision-new.org:8789/live/gowant/faojuy/3595.ts&amp;streamtype=TSDOWNLOADER&amp;name=|IT|LA7d</link> 
        </item> 
          <item> 
            <title>|IT|TV8</title> 
            <link>plugin://plugin.video.f4mTester/?url=http://iptvpro.vision-new.org:8789/live/gowant/faojuy/1128.ts&amp;streamtype=TSDOWNLOADER&amp;name=|IT|TV8</link> 
        </item> 
          <item> 
            <title>|IT|MEDIASÉT.EXTRA</title> 
            <link>plugin://plugin.video.f4mTester/?url=http://iptvpro.vision-new.org:8789/live/gowant/faojuy/1576.ts&amp;streamtype=TSDOWNLOADER&amp;name=|IT|MEDIASÉT.EXTRA</link> 
        </item> 
          <item> 
            <title>|IT|MEDIASET.ITALA.2</title> 
            <link>plugin://plugin.video.f4mTester/?url=http://iptvpro.vision-new.org:8789/live/gowant/faojuy/3697.ts&amp;streamtype=TSDOWNLOADER&amp;name=|IT|MEDIASET.ITALA.2</link> 
        </item> 
          <item> 
            <title>|IT|TGCOM</title> 
            <link>plugin://plugin.video.f4mTester/?url=http://iptvpro.vision-new.org:8789/live/gowant/faojuy/3709.ts&amp;streamtype=TSDOWNLOADER&amp;name=|IT|TGCOM</link> 
        </item> 
          <item> 
            <title>|IT|SKYTG.24.HD</title> 
            <link>plugin://plugin.video.f4mTester/?url=http://iptvpro.vision-new.org:8789/live/gowant/faojuy/598.ts&amp;streamtype=TSDOWNLOADER&amp;name=|IT|SKYTG.24.HD</link> 
        </item> 
          <item> 
            <title>|IT|RSI.LA.1</title> 
            <link>plugin://plugin.video.f4mTester/?url=http://iptvpro.vision-new.org:8789/live/gowant/faojuy/1129.ts&amp;streamtype=TSDOWNLOADER&amp;name=|IT|RSI.LA.1</link> 
        </item> 
          <item> 
            <title>|IT|RSI.LA.2</title> 
            <link>plugin://plugin.video.f4mTester/?url=http://iptvpro.vision-new.org:8789/live/gowant/faojuy/1130.ts&amp;streamtype=TSDOWNLOADER&amp;name=|IT|RSI.LA.2</link> 
        </item> 
          <item> 
            <title>---------Cinema_ita----------</title> 
            <link>plugin://plugin.video.f4mTester/?url=http://iptvpro.vision-new.org:8789/live/gowant/faojuy/433.ts&amp;streamtype=TSDOWNLOADER&amp;name=---------Cinema_ita----------</link> 
        </item> 
          <item> 
            <title>|IT|SKY.CINEMA.UNO</title> 
            <link>plugin://plugin.video.f4mTester/?url=http://iptvpro.vision-new.org:8789/live/gowant/faojuy/3680.ts&amp;streamtype=TSDOWNLOADER&amp;name=|IT|SKY.CINEMA.UNO</link> 
        </item> 
          <item> 
            <title>|IT|SKY.CINEMA.UNO+1</title> 
            <link>plugin://plugin.video.f4mTester/?url=http://iptvpro.vision-new.org:8789/live/gowant/faojuy/3606.ts&amp;streamtype=TSDOWNLOADER&amp;name=|IT|SKY.CINEMA.UNO+1</link> 
        </item> 
          <item> 
            <title>|IT|SKY.CINEMA.24.HD</title> 
            <link>plugin://plugin.video.f4mTester/?url=http://iptvpro.vision-new.org:8789/live/gowant/faojuy/1616.ts&amp;streamtype=TSDOWNLOADER&amp;name=|IT|SKY.CINEMA.24.HD</link> 
        </item> 
          <item> 
            <title>|IT|SKY.CINEMA.HITS.HD</title> 
            <link>plugin://plugin.video.f4mTester/?url=http://iptvpro.vision-new.org:8789/live/gowant/faojuy/1615.ts&amp;streamtype=TSDOWNLOADER&amp;name=|IT|SKY.CINEMA.HITS.HD</link> 
        </item> 
          <item> 
            <title>|IT|SKY.CINEMA.FAMILY.HD</title> 
            <link>plugin://plugin.video.f4mTester/?url=http://iptvpro.vision-new.org:8789/live/gowant/faojuy/3687.ts&amp;streamtype=TSDOWNLOADER&amp;name=|IT|SKY.CINEMA.FAMILY.HD</link> 
        </item> 
          <item> 
            <title>|IT|SKY.CINEMA.FAMILY+1</title> 
            <link>plugin://plugin.video.f4mTester/?url=http://iptvpro.vision-new.org:8789/live/gowant/faojuy/3666.ts&amp;streamtype=TSDOWNLOADER&amp;name=|IT|SKY.CINEMA.FAMILY+1</link> 
        </item> 
          <item> 
            <title>|IT|SKY.CINEMA.PASSION.HD</title> 
            <link>plugin://plugin.video.f4mTester/?url=http://iptvpro.vision-new.org:8789/live/gowant/faojuy/507.ts&amp;streamtype=TSDOWNLOADER&amp;name=|IT|SKY.CINEMA.PASSION.HD</link> 
        </item> 
          <item> 
            <title>|IT|SKY-CINEMA-PASSION.HD</title> 
            <link>plugin://plugin.video.f4mTester/?url=http://iptvpro.vision-new.org:8789/live/gowant/faojuy/3688.ts&amp;streamtype=TSDOWNLOADER&amp;name=|IT|SKY-CINEMA-PASSION.HD</link> 
        </item> 
          <item> 
            <title>|IT|SKY.CINEMA.COMEDY.HD</title> 
            <link>plugin://plugin.video.f4mTester/?url=http://iptvpro.vision-new.org:8789/live/gowant/faojuy/3689.ts&amp;streamtype=TSDOWNLOADER&amp;name=|IT|SKY.CINEMA.COMEDY.HD</link> 
        </item> 
          <item> 
            <title>|IT|SKY.CINEMA.MAX</title> 
            <link>plugin://plugin.video.f4mTester/?url=http://iptvpro.vision-new.org:8789/live/gowant/faojuy/3683.ts&amp;streamtype=TSDOWNLOADER&amp;name=|IT|SKY.CINEMA.MAX</link> 
        </item> 
          <item> 
            <title>|IT|SKY_CINEMA_MAX+1</title> 
            <link>plugin://plugin.video.f4mTester/?url=http://iptvpro.vision-new.org:8789/live/gowant/faojuy/3667.ts&amp;streamtype=TSDOWNLOADER&amp;name=|IT|SKY_CINEMA_MAX+1</link> 
        </item> 
          <item> 
            <title>|IT|SKY.CINEMA.CULT.HD</title> 
            <link>plugin://plugin.video.f4mTester/?url=http://iptvpro.vision-new.org:8789/live/gowant/faojuy/3691.ts&amp;streamtype=TSDOWNLOADER&amp;name=|IT|SKY.CINEMA.CULT.HD</link> 
        </item> 
          <item> 
            <title>|IT|SKY.CINEMA.CLASSIC.HD</title> 
            <link>plugin://plugin.video.f4mTester/?url=http://iptvpro.vision-new.org:8789/live/gowant/faojuy/3693.ts&amp;streamtype=TSDOWNLOADER&amp;name=|IT|SKY.CINEMA.CLASSIC.HD</link> 
        </item> 
          <item> 
            <title>|IT|PARAMOUNT-CHANNEL</title> 
            <link>plugin://plugin.video.f4mTester/?url=http://iptvpro.vision-new.org:8789/live/gowant/faojuy/3607.ts&amp;streamtype=TSDOWNLOADER&amp;name=|IT|PARAMOUNT-CHANNEL</link> 
        </item> 
          <item> 
            <title>|IT|IRIS</title> 
            <link>plugin://plugin.video.f4mTester/?url=http://iptvpro.vision-new.org:8789/live/gowant/faojuy/3608.ts&amp;streamtype=TSDOWNLOADER&amp;name=|IT|IRIS</link> 
        </item> 
          <item> 
            <title>|IT|SKY.CINEMA.3D</title> 
            <link>plugin://plugin.video.f4mTester/?url=http://iptvpro.vision-new.org:8789/live/gowant/faojuy/3702.ts&amp;streamtype=TSDOWNLOADER&amp;name=|IT|SKY.CINEMA.3D</link> 
        </item> 
          <item> 
            <title>---------- Intrattenimento ----------</title> 
            <link>plugin://plugin.video.f4mTester/?url=http://iptvpro.vision-new.org:8789/live/gowant/faojuy/1570.ts&amp;streamtype=TSDOWNLOADER&amp;name=---------- Intrattenimento ----------</link> 
        </item> 
          <item> 
            <title>|IT|SKY.UNO.HD</title> 
            <link>plugin://plugin.video.f4mTester/?url=http://iptvpro.vision-new.org:8789/live/gowant/faojuy/1571.ts&amp;streamtype=TSDOWNLOADER&amp;name=|IT|SKY.UNO.HD</link> 
        </item> 
          <item> 
            <title>|IT|SKY-UNO+1.HD</title> 
            <link>plugin://plugin.video.f4mTester/?url=http://iptvpro.vision-new.org:8789/live/gowant/faojuy/3694.ts&amp;streamtype=TSDOWNLOADER&amp;name=|IT|SKY-UNO+1.HD</link> 
        </item> 
          <item> 
            <title>|IT|SKY ATLANTIC</title> 
            <link>plugin://plugin.video.f4mTester/?url=http://iptvpro.vision-new.org:8789/live/gowant/faojuy/3684.ts&amp;streamtype=TSDOWNLOADER&amp;name=|IT|SKY ATLANTIC</link> 
        </item> 
          <item> 
            <title>|IT|SKY.ATLANTIC+1</title> 
            <link>plugin://plugin.video.f4mTester/?url=http://iptvpro.vision-new.org:8789/live/gowant/faojuy/3695.ts&amp;streamtype=TSDOWNLOADER&amp;name=|IT|SKY.ATLANTIC+1</link> 
        </item> 
          <item> 
            <title>|IT|FOX.HD</title> 
            <link>plugin://plugin.video.f4mTester/?url=http://iptvpro.vision-new.org:8789/live/gowant/faojuy/3570.ts&amp;streamtype=TSDOWNLOADER&amp;name=|IT|FOX.HD</link> 
        </item> 
          <item> 
            <title>|IT|FOX.LIFE.HD</title> 
            <link>plugin://plugin.video.f4mTester/?url=http://iptvpro.vision-new.org:8789/live/gowant/faojuy/3569.ts&amp;streamtype=TSDOWNLOADER&amp;name=|IT|FOX.LIFE.HD</link> 
        </item> 
          <item> 
            <title>|IT|FOX.CRIME</title> 
            <link>plugin://plugin.video.f4mTester/?url=http://iptvpro.vision-new.org:8789/live/gowant/faojuy/3571.ts&amp;streamtype=TSDOWNLOADER&amp;name=|IT|FOX.CRIME</link> 
        </item> 
          <item> 
            <title>|IT|FOX ANIMATION</title> 
            <link>plugin://plugin.video.f4mTester/?url=http://iptvpro.vision-new.org:8789/live/gowant/faojuy/3572.ts&amp;streamtype=TSDOWNLOADER&amp;name=|IT|FOX ANIMATION</link> 
        </item> 
          <item> 
            <title>|IT|FOX.COMEDY HD</title> 
            <link>plugin://plugin.video.f4mTester/?url=http://iptvpro.vision-new.org:8789/live/gowant/faojuy/1575.ts&amp;streamtype=TSDOWNLOADER&amp;name=|IT|FOX.COMEDY HD</link> 
        </item> 
          <item> 
            <title>|IT|COMEDY.CENTRAL</title> 
            <link>plugin://plugin.video.f4mTester/?url=http://iptvpro.vision-new.org:8789/live/gowant/faojuy/3596.ts&amp;streamtype=TSDOWNLOADER&amp;name=|IT|COMEDY.CENTRAL</link> 
        </item> 
          <item> 
            <title>|IT|REAL.TIME</title> 
            <link>plugin://plugin.video.f4mTester/?url=http://iptvpro.vision-new.org:8789/live/gowant/faojuy/1577.ts&amp;streamtype=TSDOWNLOADER&amp;name=|IT|REAL.TIME</link> 
        </item> 
          <item> 
            <title>|IT|ALICE</title> 
            <link>plugin://plugin.video.f4mTester/?url=http://iptvpro.vision-new.org:8789/live/gowant/faojuy/3575.ts&amp;streamtype=TSDOWNLOADER&amp;name=|IT|ALICE</link> 
        </item> 
          <item> 
            <title>|IT|CIELO.HD</title> 
            <link>plugin://plugin.video.f4mTester/?url=http://iptvpro.vision-new.org:8789/live/gowant/faojuy/3703.ts&amp;streamtype=TSDOWNLOADER&amp;name=|IT|CIELO.HD</link> 
        </item> 
          <item> 
            <title>|IT|CLASSICA</title> 
            <link>plugin://plugin.video.f4mTester/?url=http://iptvpro.vision-new.org:8789/live/gowant/faojuy/3721.ts&amp;streamtype=TSDOWNLOADER&amp;name=|IT|CLASSICA</link> 
        </item> 
          <item> 
            <title>|IT|LEI</title> 
            <link>plugin://plugin.video.f4mTester/?url=http://iptvpro.vision-new.org:8789/live/gowant/faojuy/3669.ts&amp;streamtype=TSDOWNLOADER&amp;name=|IT|LEI</link> 
        </item> 
          <item> 
            <title>|IT|NOVE_TV</title> 
            <link>plugin://plugin.video.f4mTester/?url=http://iptvpro.vision-new.org:8789/live/gowant/faojuy/3665.ts&amp;streamtype=TSDOWNLOADER&amp;name=|IT|NOVE_TV</link> 
        </item> 
          <item> 
            <title>|IT|SKY.ARTE.HD</title> 
            <link>plugin://plugin.video.f4mTester/?url=http://iptvpro.vision-new.org:8789/live/gowant/faojuy/3720.ts&amp;streamtype=TSDOWNLOADER&amp;name=|IT|SKY.ARTE.HD</link> 
        </item> 
          <item> 
            <title>|IT|Sposa-HD</title> 
            <link>plugin://plugin.video.f4mTester/?url=http://iptvpro.vision-new.org:8789/live/gowant/faojuy/3597.ts&amp;streamtype=TSDOWNLOADER&amp;name=|IT|Sposa-HD</link> 
        </item> 
          <item> 
            <title>---------Sport----------</title> 
            <link>plugin://plugin.video.f4mTester/?url=http://iptvpro.vision-new.org:8789/live/gowant/faojuy/434.ts&amp;streamtype=TSDOWNLOADER&amp;name=---------Sport----------</link> 
        </item> 
          <item> 
            <title>|IT|SKY.SPORT+24.HD</title> 
            <link>plugin://plugin.video.f4mTester/?url=http://iptvpro.vision-new.org:8789/live/gowant/faojuy/3699.ts&amp;streamtype=TSDOWNLOADER&amp;name=|IT|SKY.SPORT+24.HD</link> 
        </item> 
          <item> 
            <title>|IT|SKY.SPORT1.HD</title> 
            <link>plugin://plugin.video.f4mTester/?url=http://iptvpro.vision-new.org:8789/live/gowant/faojuy/3690.ts&amp;streamtype=TSDOWNLOADER&amp;name=|IT|SKY.SPORT1.HD</link> 
        </item> 
          <item> 
            <title>|IT|SKY.SPORT2.HD</title> 
            <link>plugin://plugin.video.f4mTester/?url=http://iptvpro.vision-new.org:8789/live/gowant/faojuy/528.ts&amp;streamtype=TSDOWNLOADER&amp;name=|IT|SKY.SPORT2.HD</link> 
        </item> 
          <item> 
            <title>|IT|SKY.SPORT3.HD</title> 
            <link>plugin://plugin.video.f4mTester/?url=http://iptvpro.vision-new.org:8789/live/gowant/faojuy/3505.ts&amp;streamtype=TSDOWNLOADER&amp;name=|IT|SKY.SPORT3.HD</link> 
        </item> 
          <item> 
            <title>|IT|SKY.SPORT.MIX.HD</title> 
            <link>plugin://plugin.video.f4mTester/?url=http://iptvpro.vision-new.org:8789/live/gowant/faojuy/3700.ts&amp;streamtype=TSDOWNLOADER&amp;name=|IT|SKY.SPORT.MIX.HD</link> 
        </item> 
          <item> 
            <title>|IT|SKY.SPORT.HD</title> 
            <link>plugin://plugin.video.f4mTester/?url=http://iptvpro.vision-new.org:8789/live/gowant/faojuy/3503.ts&amp;streamtype=TSDOWNLOADER&amp;name=|IT|SKY.SPORT.HD</link> 
        </item> 
          <item> 
            <title>|IT|SKY.SUPER.CALCIO.HD</title> 
            <link>plugin://plugin.video.f4mTester/?url=http://iptvpro.vision-new.org:8789/live/gowant/faojuy/3579.ts&amp;streamtype=TSDOWNLOADER&amp;name=|IT|SKY.SUPER.CALCIO.HD</link> 
        </item> 
          <item> 
            <title>|IT|FOX.SPORT</title> 
            <link>plugin://plugin.video.f4mTester/?url=http://iptvpro.vision-new.org:8789/live/gowant/faojuy/3672.ts&amp;streamtype=TSDOWNLOADER&amp;name=|IT|FOX.SPORT</link> 
        </item> 
          <item> 
            <title>|IT|SKY-SPORT-F1</title> 
            <link>plugin://plugin.video.f4mTester/?url=http://iptvpro.vision-new.org:8789/live/gowant/faojuy/531.ts&amp;streamtype=TSDOWNLOADER&amp;name=|IT|SKY-SPORT-F1</link> 
        </item> 
          <item> 
            <title>|IT|SKY.MOTO.GP</title> 
            <link>plugin://plugin.video.f4mTester/?url=http://iptvpro.vision-new.org:8789/live/gowant/faojuy/3506.ts&amp;streamtype=TSDOWNLOADER&amp;name=|IT|SKY.MOTO.GP</link> 
        </item> 
          <item> 
            <title>|IT|EUROSPORT1.HD</title> 
            <link>plugin://plugin.video.f4mTester/?url=http://iptvpro.vision-new.org:8789/live/gowant/faojuy/584.ts&amp;streamtype=TSDOWNLOADER&amp;name=|IT|EUROSPORT1.HD</link> 
        </item> 
          <item> 
            <title>|IT|EUROSPORT2.HD</title> 
            <link>plugin://plugin.video.f4mTester/?url=http://iptvpro.vision-new.org:8789/live/gowant/faojuy/585.ts&amp;streamtype=TSDOWNLOADER&amp;name=|IT|EUROSPORT2.HD</link> 
        </item> 
          <item> 
            <title>|IT|SUPER.TENNIS.HD</title> 
            <link>plugin://plugin.video.f4mTester/?url=http://iptvpro.vision-new.org:8789/live/gowant/faojuy/1578.ts&amp;streamtype=TSDOWNLOADER&amp;name=|IT|SUPER.TENNIS.HD</link> 
        </item> 
          <item> 
            <title>|IT|BIKE-CHANNEL.HD</title> 
            <link>plugin://plugin.video.f4mTester/?url=http://iptvpro.vision-new.org:8789/live/gowant/faojuy/3612.ts&amp;streamtype=TSDOWNLOADER&amp;name=|IT|BIKE-CHANNEL.HD</link> 
        </item> 
          <item> 
            <title>|IT|AUTOMOTO</title> 
            <link>plugin://plugin.video.f4mTester/?url=http://iptvpro.vision-new.org:8789/live/gowant/faojuy/3704.ts&amp;streamtype=TSDOWNLOADER&amp;name=|IT|AUTOMOTO</link> 
        </item> 
          <item> 
            <title>|IT|JUVENTUS.TV</title> 
            <link>plugin://plugin.video.f4mTester/?url=http://iptvpro.vision-new.org:8789/live/gowant/faojuy/1866.ts&amp;streamtype=TSDOWNLOADER&amp;name=|IT|JUVENTUS.TV</link> 
        </item> 
          <item> 
            <title>|IT|MILAN.CHANNEL</title> 
            <link>plugin://plugin.video.f4mTester/?url=http://iptvpro.vision-new.org:8789/live/gowant/faojuy/3565.ts&amp;streamtype=TSDOWNLOADER&amp;name=|IT|MILAN.CHANNEL</link> 
        </item> 
          <item> 
            <title>|IT|INTER-CHANNEL</title> 
            <link>plugin://plugin.video.f4mTester/?url=http://iptvpro.vision-new.org:8789/live/gowant/faojuy/3568.ts&amp;streamtype=TSDOWNLOADER&amp;name=|IT|INTER-CHANNEL</link> 
        </item> 
          <item> 
            <title>|IT|LAZIO.CHANNEL</title> 
            <link>plugin://plugin.video.f4mTester/?url=http://iptvpro.vision-new.org:8789/live/gowant/faojuy/3593.ts&amp;streamtype=TSDOWNLOADER&amp;name=|IT|LAZIO.CHANNEL</link> 
        </item> 
          <item> 
            <title>|IT|ROMA.TV</title> 
            <link>plugin://plugin.video.f4mTester/?url=http://iptvpro.vision-new.org:8789/live/gowant/faojuy/1867.ts&amp;streamtype=TSDOWNLOADER&amp;name=|IT|ROMA.TV</link> 
        </item> 
          <item> 
            <title>|IT|RAI.SPORT.1</title> 
            <link>plugin://plugin.video.f4mTester/?url=http://iptvpro.vision-new.org:8789/live/gowant/faojuy/3671.ts&amp;streamtype=TSDOWNLOADER&amp;name=|IT|RAI.SPORT.1</link> 
        </item> 
          <item> 
            <title>|IT|FIGHT_BOX</title> 
            <link>plugin://plugin.video.f4mTester/?url=http://iptvpro.vision-new.org:8789/live/gowant/faojuy/3610.ts&amp;streamtype=TSDOWNLOADER&amp;name=|IT|FIGHT_BOX</link> 
        </item> 
          <item> 
            <title>|IT|SPORT-ITALIA</title> 
            <link>plugin://plugin.video.f4mTester/?url=http://iptvpro.vision-new.org:8789/live/gowant/faojuy/3701.ts&amp;streamtype=TSDOWNLOADER&amp;name=|IT|SPORT-ITALIA</link> 
        </item> 
          <item> 
            <title>|IT|TOP-CALCIO.24</title> 
            <link>plugin://plugin.video.f4mTester/?url=http://iptvpro.vision-new.org:8789/live/gowant/faojuy/3614.ts&amp;streamtype=TSDOWNLOADER&amp;name=|IT|TOP-CALCIO.24</link> 
        </item> 
          <item> 
            <title>++++Calcio++++</title> 
            <link>plugin://plugin.video.f4mTester/?url=http://iptvpro.vision-new.org:8789/live/gowant/faojuy/524.ts&amp;streamtype=TSDOWNLOADER&amp;name=++++Calcio++++</link> 
        </item> 
          <item> 
            <title>|IT|SKY_CALCIO1</title> 
            <link>plugin://plugin.video.f4mTester/?url=http://iptvpro.vision-new.org:8789/live/gowant/faojuy/3599.ts&amp;streamtype=TSDOWNLOADER&amp;name=|IT|SKY_CALCIO1</link> 
        </item> 
          <item> 
            <title>|IT|SKY_CALCIO2</title> 
            <link>plugin://plugin.video.f4mTester/?url=http://iptvpro.vision-new.org:8789/live/gowant/faojuy/3600.ts&amp;streamtype=TSDOWNLOADER&amp;name=|IT|SKY_CALCIO2</link> 
        </item> 
          <item> 
            <title>|IT|SKY_CALCIO3</title> 
            <link>plugin://plugin.video.f4mTester/?url=http://iptvpro.vision-new.org:8789/live/gowant/faojuy/3601.ts&amp;streamtype=TSDOWNLOADER&amp;name=|IT|SKY_CALCIO3</link> 
        </item> 
          <item> 
            <title>|IT|SKY_CALCIO4</title> 
            <link>plugin://plugin.video.f4mTester/?url=http://iptvpro.vision-new.org:8789/live/gowant/faojuy/3602.ts&amp;streamtype=TSDOWNLOADER&amp;name=|IT|SKY_CALCIO4</link> 
        </item> 
          <item> 
            <title>|IT|SKY_CALCIO5</title> 
            <link>plugin://plugin.video.f4mTester/?url=http://iptvpro.vision-new.org:8789/live/gowant/faojuy/3603.ts&amp;streamtype=TSDOWNLOADER&amp;name=|IT|SKY_CALCIO5</link> 
        </item> 
          <item> 
            <title>|IT|SKY_CALCIO6</title> 
            <link>plugin://plugin.video.f4mTester/?url=http://iptvpro.vision-new.org:8789/live/gowant/faojuy/3604.ts&amp;streamtype=TSDOWNLOADER&amp;name=|IT|SKY_CALCIO6</link> 
        </item> 
          <item> 
            <title>|IT|SKY.CALCIO.7</title> 
            <link>plugin://plugin.video.f4mTester/?url=http://iptvpro.vision-new.org:8789/live/gowant/faojuy/395.ts&amp;streamtype=TSDOWNLOADER&amp;name=|IT|SKY.CALCIO.7</link> 
        </item> 
          <item> 
            <title>|IT|*****CULTURA*****|IT|</title> 
            <link>plugin://plugin.video.f4mTester/?url=http://iptvpro.vision-new.org:8789/live/gowant/faojuy/525.ts&amp;streamtype=TSDOWNLOADER&amp;name=|IT|*****CULTURA*****|IT|</link> 
        </item> 
          <item> 
            <title>|IT|DISCOVERY.CHANNEL</title> 
            <link>plugin://plugin.video.f4mTester/?url=http://iptvpro.vision-new.org:8789/live/gowant/faojuy/3718.ts&amp;streamtype=TSDOWNLOADER&amp;name=|IT|DISCOVERY.CHANNEL</link> 
        </item> 
          <item> 
            <title>|IT|DISCOVERY.SCIENCE</title> 
            <link>plugin://plugin.video.f4mTester/?url=http://iptvpro.vision-new.org:8789/live/gowant/faojuy/3719.ts&amp;streamtype=TSDOWNLOADER&amp;name=|IT|DISCOVERY.SCIENCE</link> 
        </item> 
          <item> 
            <title>|IT|Crime.&amp;.Investigation-HD</title> 
            <link>plugin://plugin.video.f4mTester/?url=http://iptvpro.vision-new.org:8789/live/gowant/faojuy/3574.ts&amp;streamtype=TSDOWNLOADER&amp;name=|IT|Crime.&amp;.Investigation-HD</link> 
        </item> 
          <item> 
            <title>|IT|DISCOVERY.HD</title> 
            <link>plugin://plugin.video.f4mTester/?url=http://iptvpro.vision-new.org:8789/live/gowant/faojuy/509.ts&amp;streamtype=TSDOWNLOADER&amp;name=|IT|DISCOVERY.HD</link> 
        </item> 
          <item> 
            <title>|IT|RAI.SPORT.2</title> 
            <link>plugin://plugin.video.f4mTester/?url=http://iptvpro.vision-new.org:8789/live/gowant/faojuy/1574.ts&amp;streamtype=TSDOWNLOADER&amp;name=|IT|RAI.SPORT.2</link> 
        </item> 
          <item> 
            <title>|IT|RAI_NEWS_24</title> 
            <link>plugin://plugin.video.f4mTester/?url=http://iptvpro.vision-new.org:8789/live/gowant/faojuy/150.ts&amp;streamtype=TSDOWNLOADER&amp;name=|IT|RAI_NEWS_24</link> 
        </item> 
          <item> 
            <title>|IT|SKY.CALCIO.1</title> 
            <link>plugin://plugin.video.f4mTester/?url=http://iptvpro.vision-new.org:8789/live/gowant/faojuy/3710.ts&amp;streamtype=TSDOWNLOADER&amp;name=|IT|SKY.CALCIO.1</link> 
        </item> 
          <item> 
            <title>|IT|SKY.CALCIO.2</title> 
            <link>plugin://plugin.video.f4mTester/?url=http://iptvpro.vision-new.org:8789/live/gowant/faojuy/3712.ts&amp;streamtype=TSDOWNLOADER&amp;name=|IT|SKY.CALCIO.2</link> 
        </item> 
          <item> 
            <title>|IT|SKY.CALCIO.3</title> 
            <link>plugin://plugin.video.f4mTester/?url=http://iptvpro.vision-new.org:8789/live/gowant/faojuy/3713.ts&amp;streamtype=TSDOWNLOADER&amp;name=|IT|SKY.CALCIO.3</link> 
        </item> 
          <item> 
            <title>|IT|SKY.CALCIO.4</title> 
            <link>plugin://plugin.video.f4mTester/?url=http://iptvpro.vision-new.org:8789/live/gowant/faojuy/3714.ts&amp;streamtype=TSDOWNLOADER&amp;name=|IT|SKY.CALCIO.4</link> 
        </item> 
          <item> 
            <title>|IT|SKY.CALCIO.5</title> 
            <link>plugin://plugin.video.f4mTester/?url=http://iptvpro.vision-new.org:8789/live/gowant/faojuy/3715.ts&amp;streamtype=TSDOWNLOADER&amp;name=|IT|SKY.CALCIO.5</link> 
        </item> 
          <item> 
            <title>|IT|SKY.CALCIO.6</title> 
            <link>plugin://plugin.video.f4mTester/?url=http://iptvpro.vision-new.org:8789/live/gowant/faojuy/3716.ts&amp;streamtype=TSDOWNLOADER&amp;name=|IT|SKY.CALCIO.6</link> 
        </item> 
          <item> 
            <title>|IT|SKY.CINEMA.MAX+1.HD</title> 
            <link>plugin://plugin.video.f4mTester/?url=http://iptvpro.vision-new.org:8789/live/gowant/faojuy/3692.ts&amp;streamtype=TSDOWNLOADER&amp;name=|IT|SKY.CINEMA.MAX+1.HD</link> 
        </item> 
          <item> 
            <title>|IT|SKY_SUPERCALCIO</title> 
            <link>plugin://plugin.video.f4mTester/?url=http://iptvpro.vision-new.org:8789/live/gowant/faojuy/3576.ts&amp;streamtype=TSDOWNLOADER&amp;name=|IT|SKY_SUPERCALCIO</link> 
        </item> 
          <item> 
            <title>|IT|SPORT.ITALIA</title> 
            <link>plugin://plugin.video.f4mTester/?url=http://iptvpro.vision-new.org:8789/live/gowant/faojuy/3609.ts&amp;streamtype=TSDOWNLOADER&amp;name=|IT|SPORT.ITALIA</link> 
        </item> 
          <item> 
            <title>|IT|DISCOVERY.TRAVEL</title> 
            <link>plugin://plugin.video.f4mTester/?url=http://iptvpro.vision-new.org:8789/live/gowant/faojuy/3677.ts&amp;streamtype=TSDOWNLOADER&amp;name=|IT|DISCOVERY.TRAVEL</link> 
        </item> 
          <item> 
            <title>|IT|NAT.GEO.CHANNEL</title> 
            <link>plugin://plugin.video.f4mTester/?url=http://iptvpro.vision-new.org:8789/live/gowant/faojuy/3705.ts&amp;streamtype=TSDOWNLOADER&amp;name=|IT|NAT.GEO.CHANNEL</link> 
        </item> 
          <item> 
            <title>|IT|NAT.GEO.PEOPLE</title> 
            <link>plugin://plugin.video.f4mTester/?url=http://iptvpro.vision-new.org:8789/live/gowant/faojuy/3706.ts&amp;streamtype=TSDOWNLOADER&amp;name=|IT|NAT.GEO.PEOPLE</link> 
        </item> 
          <item> 
            <title>|IT|NAT.GEO.WILD</title> 
            <link>plugin://plugin.video.f4mTester/?url=http://iptvpro.vision-new.org:8789/live/gowant/faojuy/3707.ts&amp;streamtype=TSDOWNLOADER&amp;name=|IT|NAT.GEO.WILD</link> 
        </item> 
          <item> 
            <title>|IT|ANIMAL.PLANET</title> 
            <link>plugin://plugin.video.f4mTester/?url=http://iptvpro.vision-new.org:8789/live/gowant/faojuy/3708.ts&amp;streamtype=TSDOWNLOADER&amp;name=|IT|ANIMAL.PLANET</link> 
        </item> 
          <item> 
            <title>|IT|BLAZE</title> 
            <link>plugin://plugin.video.f4mTester/?url=http://iptvpro.vision-new.org:8789/live/gowant/faojuy/3668.ts&amp;streamtype=TSDOWNLOADER&amp;name=|IT|BLAZE</link> 
        </item> 
          <item> 
            <title>|IT|DMAX</title> 
            <link>plugin://plugin.video.f4mTester/?url=http://iptvpro.vision-new.org:8789/live/gowant/faojuy/3573.ts&amp;streamtype=TSDOWNLOADER&amp;name=|IT|DMAX</link> 
        </item> 
          <item> 
            <title>|IT|FOCUS</title> 
            <link>plugin://plugin.video.f4mTester/?url=http://iptvpro.vision-new.org:8789/live/gowant/faojuy/3711.ts&amp;streamtype=TSDOWNLOADER&amp;name=|IT|FOCUS</link> 
        </item> 
          <item> 
            <title>|IT|GAMBERO.ROSSO</title> 
            <link>plugin://plugin.video.f4mTester/?url=http://iptvpro.vision-new.org:8789/live/gowant/faojuy/3564.ts&amp;streamtype=TSDOWNLOADER&amp;name=|IT|GAMBERO.ROSSO</link> 
        </item> 
          <item> 
            <title>|IT|DOVE-TV</title> 
            <link>plugin://plugin.video.f4mTester/?url=http://iptvpro.vision-new.org:8789/live/gowant/faojuy/3674.ts&amp;streamtype=TSDOWNLOADER&amp;name=|IT|DOVE-TV</link> 
        </item> 
          <item> 
            <title>|IT|GIALLO</title> 
            <link>plugin://plugin.video.f4mTester/?url=http://iptvpro.vision-new.org:8789/live/gowant/faojuy/3685.ts&amp;streamtype=TSDOWNLOADER&amp;name=|IT|GIALLO</link> 
        </item> 
          <item> 
            <title>|IT|FINE.LIVING</title> 
            <link>plugin://plugin.video.f4mTester/?url=http://iptvpro.vision-new.org:8789/live/gowant/faojuy/3618.ts&amp;streamtype=TSDOWNLOADER&amp;name=|IT|FINE.LIVING</link> 
        </item> 
          <item> 
            <title>|IT|CACCIA.PESCA</title> 
            <link>plugin://plugin.video.f4mTester/?url=http://iptvpro.vision-new.org:8789/live/gowant/faojuy/3675.ts&amp;streamtype=TSDOWNLOADER&amp;name=|IT|CACCIA.PESCA</link> 
        </item> 
          <item> 
            <title>|IT|PESCA.CACCIA</title> 
            <link>plugin://plugin.video.f4mTester/?url=http://iptvpro.vision-new.org:8789/live/gowant/faojuy/3676.ts&amp;streamtype=TSDOWNLOADER&amp;name=|IT|PESCA.CACCIA</link> 
        </item> 
          <item> 
            <title>|IT|PESCARE-E-CACCIARE</title> 
            <link>plugin://plugin.video.f4mTester/?url=http://iptvpro.vision-new.org:8789/live/gowant/faojuy/3722.ts&amp;streamtype=TSDOWNLOADER&amp;name=|IT|PESCARE-E-CACCIARE</link> 
        </item> 
          <item> 
            <title>|IT|ITALIAN-FISHING</title> 
            <link>plugin://plugin.video.f4mTester/?url=http://iptvpro.vision-new.org:8789/live/gowant/faojuy/4038.ts&amp;streamtype=TSDOWNLOADER&amp;name=|IT|ITALIAN-FISHING</link> 
        </item> 
          <item> 
            <title>|IT|MARCO.POLO</title> 
            <link>plugin://plugin.video.f4mTester/?url=http://iptvpro.vision-new.org:8789/live/gowant/faojuy/3723.ts&amp;streamtype=TSDOWNLOADER&amp;name=|IT|MARCO.POLO</link> 
        </item> 
          <item> 
            <title>|IT|RAI.STORIA</title> 
            <link>plugin://plugin.video.f4mTester/?url=http://iptvpro.vision-new.org:8789/live/gowant/faojuy/1448.ts&amp;streamtype=TSDOWNLOADER&amp;name=|IT|RAI.STORIA</link> 
        </item> 
          <item> 
            <title>|IT|TOPCRIME</title> 
            <link>plugin://plugin.video.f4mTester/?url=http://iptvpro.vision-new.org:8789/live/gowant/faojuy/3696.ts&amp;streamtype=TSDOWNLOADER&amp;name=|IT|TOPCRIME</link> 
        </item> 
          <item> 
            <title>|IT|HISTORY-LAB</title> 
            <link>plugin://plugin.video.f4mTester/?url=http://iptvpro.vision-new.org:8789/live/gowant/faojuy/4037.ts&amp;streamtype=TSDOWNLOADER&amp;name=|IT|HISTORY-LAB</link> 
        </item> 
          <item> 
            <title>|IT|SKY.HISTORY.HD</title> 
            <link>plugin://plugin.video.f4mTester/?url=http://iptvpro.vision-new.org:8789/live/gowant/faojuy/1580.ts&amp;streamtype=TSDOWNLOADER&amp;name=|IT|SKY.HISTORY.HD</link> 
        </item> 
          <item> 
            <title>---------- Bambini ----------</title> 
            <link>plugin://plugin.video.f4mTester/?url=http://iptvpro.vision-new.org:8789/live/gowant/faojuy/1573.ts&amp;streamtype=TSDOWNLOADER&amp;name=---------- Bambini ----------</link> 
        </item> 
          <item> 
            <title>|IT|SKY.DISNEY.CHANNEL.HD</title> 
            <link>plugin://plugin.video.f4mTester/?url=http://iptvpro.vision-new.org:8789/live/gowant/faojuy/1131.ts&amp;streamtype=TSDOWNLOADER&amp;name=|IT|SKY.DISNEY.CHANNEL.HD</link> 
        </item> 
          <item> 
            <title>|IT|DISNEY.JUNIOR</title> 
            <link>plugin://plugin.video.f4mTester/?url=http://iptvpro.vision-new.org:8789/live/gowant/faojuy/3567.ts&amp;streamtype=TSDOWNLOADER&amp;name=|IT|DISNEY.JUNIOR</link> 
        </item> 
          <item> 
            <title>|IT|DISNEY.XD</title> 
            <link>plugin://plugin.video.f4mTester/?url=http://iptvpro.vision-new.org:8789/live/gowant/faojuy/3504.ts&amp;streamtype=TSDOWNLOADER&amp;name=|IT|DISNEY.XD</link> 
        </item> 
          <item> 
            <title>|IT|CARTOON.NETWORK</title> 
            <link>plugin://plugin.video.f4mTester/?url=http://iptvpro.vision-new.org:8789/live/gowant/faojuy/3717.ts&amp;streamtype=TSDOWNLOADER&amp;name=|IT|CARTOON.NETWORK</link> 
        </item> 
          <item> 
            <title>|IT|NICKELODEON</title> 
            <link>plugin://plugin.video.f4mTester/?url=http://iptvpro.vision-new.org:8789/live/gowant/faojuy/3726.ts&amp;streamtype=TSDOWNLOADER&amp;name=|IT|NICKELODEON</link> 
        </item> 
          <item> 
            <title>|IT|NICK.JR</title> 
            <link>plugin://plugin.video.f4mTester/?url=http://iptvpro.vision-new.org:8789/live/gowant/faojuy/3725.ts&amp;streamtype=TSDOWNLOADER&amp;name=|IT|NICK.JR</link> 
        </item> 
          <item> 
            <title>|IT|BOOMERANG</title> 
            <link>plugin://plugin.video.f4mTester/?url=http://iptvpro.vision-new.org:8789/live/gowant/faojuy/3727.ts&amp;streamtype=TSDOWNLOADER&amp;name=|IT|BOOMERANG</link> 
        </item> 
          <item> 
            <title>|IT|DEA.JUNIOR</title> 
            <link>plugin://plugin.video.f4mTester/?url=http://iptvpro.vision-new.org:8789/live/gowant/faojuy/3555.ts&amp;streamtype=TSDOWNLOADER&amp;name=|IT|DEA.JUNIOR</link> 
        </item> 
          <item> 
            <title>|IT|DEA.KIDS</title> 
            <link>plugin://plugin.video.f4mTester/?url=http://iptvpro.vision-new.org:8789/live/gowant/faojuy/3551.ts&amp;streamtype=TSDOWNLOADER&amp;name=|IT|DEA.KIDS</link> 
        </item> 
          <item> 
            <title>|IT|K2</title> 
            <link>plugin://plugin.video.f4mTester/?url=http://iptvpro.vision-new.org:8789/live/gowant/faojuy/3543.ts&amp;streamtype=TSDOWNLOADER&amp;name=|IT|K2</link> 
        </item> 
          <item> 
            <title>|IT|CARTOONITO</title> 
            <link>plugin://plugin.video.f4mTester/?url=http://iptvpro.vision-new.org:8789/live/gowant/faojuy/77.ts&amp;streamtype=TSDOWNLOADER&amp;name=|IT|CARTOONITO</link> 
        </item> 
          <item> 
            <title>|IT|BOING</title> 
            <link>plugin://plugin.video.f4mTester/?url=http://iptvpro.vision-new.org:8789/live/gowant/faojuy/3592.ts&amp;streamtype=TSDOWNLOADER&amp;name=|IT|BOING</link> 
        </item> 
          <item> 
            <title>|IT|FRISBEE</title> 
            <link>plugin://plugin.video.f4mTester/?url=http://iptvpro.vision-new.org:8789/live/gowant/faojuy/3686.ts&amp;streamtype=TSDOWNLOADER&amp;name=|IT|FRISBEE</link> 
        </item> 
          <item> 
            <title>|IT|MANGA</title> 
            <link>plugin://plugin.video.f4mTester/?url=http://iptvpro.vision-new.org:8789/live/gowant/faojuy/3594.ts&amp;streamtype=TSDOWNLOADER&amp;name=|IT|MANGA</link> 
        </item> 
          <item> 
            <title>|IT|POP</title> 
            <link>plugin://plugin.video.f4mTester/?url=http://iptvpro.vision-new.org:8789/live/gowant/faojuy/3678.ts&amp;streamtype=TSDOWNLOADER&amp;name=|IT|POP</link> 
        </item> 
          <item> 
            <title>|IT|SUPER</title> 
            <link>plugin://plugin.video.f4mTester/?url=http://iptvpro.vision-new.org:8789/live/gowant/faojuy/3724.ts&amp;streamtype=TSDOWNLOADER&amp;name=|IT|SUPER</link> 
        </item> 
          <item> 
            <title>|IT|*****PRIMAFILA*****|IT|</title> 
            <link>plugin://plugin.video.f4mTester/?url=http://iptvpro.vision-new.org:8789/live/gowant/faojuy/407.ts&amp;streamtype=TSDOWNLOADER&amp;name=|IT|*****PRIMAFILA*****|IT|</link> 
        </item> 
          <item> 
            <title>|IT|PRIMAFILA_1</title> 
            <link>plugin://plugin.video.f4mTester/?url=http://iptvpro.vision-new.org:8789/live/gowant/faojuy/19.ts&amp;streamtype=TSDOWNLOADER&amp;name=|IT|PRIMAFILA_1</link> 
        </item> 
          <item> 
            <title>|IT|PRIMAFILA_2</title> 
            <link>plugin://plugin.video.f4mTester/?url=http://iptvpro.vision-new.org:8789/live/gowant/faojuy/20.ts&amp;streamtype=TSDOWNLOADER&amp;name=|IT|PRIMAFILA_2</link> 
        </item> 
          <item> 
            <title>|IT|PRIMAFILA_3</title> 
            <link>plugin://plugin.video.f4mTester/?url=http://iptvpro.vision-new.org:8789/live/gowant/faojuy/21.ts&amp;streamtype=TSDOWNLOADER&amp;name=|IT|PRIMAFILA_3</link> 
        </item> 
          <item> 
            <title>|IT|PRIMAFILA_4</title> 
            <link>plugin://plugin.video.f4mTester/?url=http://iptvpro.vision-new.org:8789/live/gowant/faojuy/22.ts&amp;streamtype=TSDOWNLOADER&amp;name=|IT|PRIMAFILA_4</link> 
        </item> 
          <item> 
            <title>|IT|PRIMAFILA_5</title> 
            <link>plugin://plugin.video.f4mTester/?url=http://iptvpro.vision-new.org:8789/live/gowant/faojuy/23.ts&amp;streamtype=TSDOWNLOADER&amp;name=|IT|PRIMAFILA_5</link> 
        </item> 
          <item> 
            <title>|IT|PRIMAFILA_6</title> 
            <link>plugin://plugin.video.f4mTester/?url=http://iptvpro.vision-new.org:8789/live/gowant/faojuy/24.ts&amp;streamtype=TSDOWNLOADER&amp;name=|IT|PRIMAFILA_6</link> 
        </item> 
          <item> 
            <title>|IT|PRIMAFILA_7</title> 
            <link>plugin://plugin.video.f4mTester/?url=http://iptvpro.vision-new.org:8789/live/gowant/faojuy/25.ts&amp;streamtype=TSDOWNLOADER&amp;name=|IT|PRIMAFILA_7</link> 
        </item> 
          <item> 
            <title>|IT|PRIMAFILA_8</title> 
            <link>plugin://plugin.video.f4mTester/?url=http://iptvpro.vision-new.org:8789/live/gowant/faojuy/26.ts&amp;streamtype=TSDOWNLOADER&amp;name=|IT|PRIMAFILA_8</link> 
        </item> 
          <item> 
            <title>|IT|PRIMAFILA_9</title> 
            <link>plugin://plugin.video.f4mTester/?url=http://iptvpro.vision-new.org:8789/live/gowant/faojuy/27.ts&amp;streamtype=TSDOWNLOADER&amp;name=|IT|PRIMAFILA_9</link> 
        </item> 
          <item> 
            <title>|IT[PRIMAFILA_10</title> 
            <link>plugin://plugin.video.f4mTester/?url=http://iptvpro.vision-new.org:8789/live/gowant/faojuy/400.ts&amp;streamtype=TSDOWNLOADER&amp;name=|IT[PRIMAFILA_10</link> 
        </item> 
          <item> 
            <title>|IT|PRIMAFILA_11</title> 
            <link>plugin://plugin.video.f4mTester/?url=http://iptvpro.vision-new.org:8789/live/gowant/faojuy/401.ts&amp;streamtype=TSDOWNLOADER&amp;name=|IT|PRIMAFILA_11</link> 
        </item> 
          <item> 
            <title>|IT[PRIMAFILA_12</title> 
            <link>plugin://plugin.video.f4mTester/?url=http://iptvpro.vision-new.org:8789/live/gowant/faojuy/402.ts&amp;streamtype=TSDOWNLOADER&amp;name=|IT[PRIMAFILA_12</link> 
        </item> 
          <item> 
            <title>|IT|PRIMAFILA_13</title> 
            <link>plugin://plugin.video.f4mTester/?url=http://iptvpro.vision-new.org:8789/live/gowant/faojuy/403.ts&amp;streamtype=TSDOWNLOADER&amp;name=|IT|PRIMAFILA_13</link> 
        </item> 
          <item> 
            <title>|IT|PRIMAFILA_14</title> 
            <link>plugin://plugin.video.f4mTester/?url=http://iptvpro.vision-new.org:8789/live/gowant/faojuy/404.ts&amp;streamtype=TSDOWNLOADER&amp;name=|IT|PRIMAFILA_14</link> 
        </item> 
          <item> 
            <title>|IT|PRIMAFILA_15</title> 
            <link>plugin://plugin.video.f4mTester/?url=http://iptvpro.vision-new.org:8789/live/gowant/faojuy/405.ts&amp;streamtype=TSDOWNLOADER&amp;name=|IT|PRIMAFILA_15</link> 
        </item> 
          <item> 
            <title>|IT|PRIMAFILA_16</title> 
            <link>plugin://plugin.video.f4mTester/?url=http://iptvpro.vision-new.org:8789/live/gowant/faojuy/406.ts&amp;streamtype=TSDOWNLOADER&amp;name=|IT|PRIMAFILA_16</link> 
        </item> 
          <item> 
            <title>|IT|PRIMAFILA_17</title> 
            <link>plugin://plugin.video.f4mTester/?url=http://iptvpro.vision-new.org:8789/live/gowant/faojuy/3529.ts&amp;streamtype=TSDOWNLOADER&amp;name=|IT|PRIMAFILA_17</link> 
        </item> 
          <item> 
            <title>|IT|PRIMAFILA_18</title> 
            <link>plugin://plugin.video.f4mTester/?url=http://iptvpro.vision-new.org:8789/live/gowant/faojuy/3533.ts&amp;streamtype=TSDOWNLOADER&amp;name=|IT|PRIMAFILA_18</link> 
        </item> 
          <item> 
            <title>|IT|PRIMAFILA_19</title> 
            <link>plugin://plugin.video.f4mTester/?url=http://iptvpro.vision-new.org:8789/live/gowant/faojuy/3535.ts&amp;streamtype=TSDOWNLOADER&amp;name=|IT|PRIMAFILA_19</link> 
        </item> 
          <item> 
            <title>|IT|PRIMAFILA_20</title> 
            <link>plugin://plugin.video.f4mTester/?url=http://iptvpro.vision-new.org:8789/live/gowant/faojuy/3538.ts&amp;streamtype=TSDOWNLOADER&amp;name=|IT|PRIMAFILA_20</link> 
        </item> 
          <item> 
            <title>=====PREMIUM=====</title> 
            <link>plugin://plugin.video.f4mTester/?url=http://iptvpro.vision-new.org:8789/live/gowant/faojuy/408.ts&amp;streamtype=TSDOWNLOADER&amp;name======PREMIUM=====</link> 
        </item> 
          <item> 
            <title>|IT|PREMIUM.CINEMA.HD</title> 
            <link>plugin://plugin.video.f4mTester/?url=http://iptvpro.vision-new.org:8789/live/gowant/faojuy/3588.ts&amp;streamtype=TSDOWNLOADER&amp;name=|IT|PREMIUM.CINEMA.HD</link> 
        </item> 
          <item> 
            <title>|IT|PREMIUM.CINEMA+24</title> 
            <link>plugin://plugin.video.f4mTester/?url=http://iptvpro.vision-new.org:8789/live/gowant/faojuy/11.ts&amp;streamtype=TSDOWNLOADER&amp;name=|IT|PREMIUM.CINEMA+24</link> 
        </item> 
          <item> 
            <title>|IT|PREMIUM.CINEMA2</title> 
            <link>plugin://plugin.video.f4mTester/?url=http://iptvpro.vision-new.org:8789/live/gowant/faojuy/3679.ts&amp;streamtype=TSDOWNLOADER&amp;name=|IT|PREMIUM.CINEMA2</link> 
        </item> 
          <item> 
            <title>|IT|PREMIUM.CINEMA2+24</title> 
            <link>plugin://plugin.video.f4mTester/?url=http://iptvpro.vision-new.org:8789/live/gowant/faojuy/3681.ts&amp;streamtype=TSDOWNLOADER&amp;name=|IT|PREMIUM.CINEMA2+24</link> 
        </item> 
          <item> 
            <title>|IT|PREMIUM.CINEMA.ACTION</title> 
            <link>plugin://plugin.video.f4mTester/?url=http://iptvpro.vision-new.org:8789/live/gowant/faojuy/2.ts&amp;streamtype=TSDOWNLOADER&amp;name=|IT|PREMIUM.CINEMA.ACTION</link> 
        </item> 
          <item> 
            <title>|IT|PREMIUM.CINEMA.ACTION+24</title> 
            <link>plugin://plugin.video.f4mTester/?url=http://iptvpro.vision-new.org:8789/live/gowant/faojuy/1585.ts&amp;streamtype=TSDOWNLOADER&amp;name=|IT|PREMIUM.CINEMA.ACTION+24</link> 
        </item> 
          <item> 
            <title>|IT|PREMIUM.ENERGY</title> 
            <link>plugin://plugin.video.f4mTester/?url=http://iptvpro.vision-new.org:8789/live/gowant/faojuy/3583.ts&amp;streamtype=TSDOWNLOADER&amp;name=|IT|PREMIUM.ENERGY</link> 
        </item> 
          <item> 
            <title>|IT|PREMIUM.ENERGY+24</title> 
            <link>plugin://plugin.video.f4mTester/?url=http://iptvpro.vision-new.org:8789/live/gowant/faojuy/3728.ts&amp;streamtype=TSDOWNLOADER&amp;name=|IT|PREMIUM.ENERGY+24</link> 
        </item> 
          <item> 
            <title>|IT|Premium-Emotion</title> 
            <link>plugin://plugin.video.f4mTester/?url=http://iptvpro.vision-new.org:8789/live/gowant/faojuy/3584.ts&amp;streamtype=TSDOWNLOADER&amp;name=|IT|Premium-Emotion</link> 
        </item> 
          <item> 
            <title>|IT|PREMIUM.COMEDY</title> 
            <link>plugin://plugin.video.f4mTester/?url=http://iptvpro.vision-new.org:8789/live/gowant/faojuy/3587.ts&amp;streamtype=TSDOWNLOADER&amp;name=|IT|PREMIUM.COMEDY</link> 
        </item> 
          <item> 
            <title>|IT|PREMIUM.CRIME</title> 
            <link>plugin://plugin.video.f4mTester/?url=http://iptvpro.vision-new.org:8789/live/gowant/faojuy/3586.ts&amp;streamtype=TSDOWNLOADER&amp;name=|IT|PREMIUM.CRIME</link> 
        </item> 
          <item> 
            <title>|IT|PREMIUM.CRIME+24</title> 
            <link>plugin://plugin.video.f4mTester/?url=http://iptvpro.vision-new.org:8789/live/gowant/faojuy/3585.ts&amp;streamtype=TSDOWNLOADER&amp;name=|IT|PREMIUM.CRIME+24</link> 
        </item> 
          <item> 
            <title>|IT|PREMIUM.STORIES</title> 
            <link>plugin://plugin.video.f4mTester/?url=http://iptvpro.vision-new.org:8789/live/gowant/faojuy/3581.ts&amp;streamtype=TSDOWNLOADER&amp;name=|IT|PREMIUM.STORIES</link> 
        </item> 
          <item> 
            <title>|IT|PREMIUM.JOI</title> 
            <link>plugin://plugin.video.f4mTester/?url=http://iptvpro.vision-new.org:8789/live/gowant/faojuy/3582.ts&amp;streamtype=TSDOWNLOADER&amp;name=|IT|PREMIUM.JOI</link> 
        </item> 
          <item> 
            <title>|IT|FOX</title> 
            <link>plugin://plugin.video.f4mTester/?url=http://iptvpro.vision-new.org:8789/live/gowant/faojuy/3566.ts&amp;streamtype=TSDOWNLOADER&amp;name=|IT|FOX</link> 
        </item> 
          <item> 
            <title>|IT|Premium-Cinema-Emotion</title> 
            <link>plugin://plugin.video.f4mTester/?url=http://iptvpro.vision-new.org:8789/live/gowant/faojuy/1583.ts&amp;streamtype=TSDOWNLOADER&amp;name=|IT|Premium-Cinema-Emotion</link> 
        </item> 
          <item> 
            <title>|IT|PREMIUM.JOI+24</title> 
            <link>plugin://plugin.video.f4mTester/?url=http://iptvpro.vision-new.org:8789/live/gowant/faojuy/3729.ts&amp;streamtype=TSDOWNLOADER&amp;name=|IT|PREMIUM.JOI+24</link> 
        </item> 
          <item> 
            <title>|IT|PREMIUM.CARTOON.NETWORK</title> 
            <link>plugin://plugin.video.f4mTester/?url=http://iptvpro.vision-new.org:8789/live/gowant/faojuy/3589.ts&amp;streamtype=TSDOWNLOADER&amp;name=|IT|PREMIUM.CARTOON.NETWORK</link> 
        </item> 
          <item> 
            <title>|IT|PREMIUM-SPORT.2</title> 
            <link>plugin://plugin.video.f4mTester/?url=http://iptvpro.vision-new.org:8789/live/gowant/faojuy/3682.ts&amp;streamtype=TSDOWNLOADER&amp;name=|IT|PREMIUM-SPORT.2</link> 
        </item> 
          <item> 
            <title>|IT|PREMIUM.STUDIO.UNIVERSAL</title> 
            <link>plugin://plugin.video.f4mTester/?url=http://iptvpro.vision-new.org:8789/live/gowant/faojuy/3580.ts&amp;streamtype=TSDOWNLOADER&amp;name=|IT|PREMIUM.STUDIO.UNIVERSAL</link> 
        </item> 
          <item> 
            <title>PREMIUM_STUDIO_UNIVERSAL</title> 
            <link>plugin://plugin.video.f4mTester/?url=http://iptvpro.vision-new.org:8789/live/gowant/faojuy/18.ts&amp;streamtype=TSDOWNLOADER&amp;name=PREMIUM_STUDIO_UNIVERSAL</link> 
        </item> 
          <item> 
            <title>|IT|PREMIUM-Discovery-Investigation</title> 
            <link>plugin://plugin.video.f4mTester/?url=http://iptvpro.vision-new.org:8789/live/gowant/faojuy/3730.ts&amp;streamtype=TSDOWNLOADER&amp;name=|IT|PREMIUM-Discovery-Investigation</link> 
        </item> 
          <item> 
            <title>|IT|PREMIUM.SPORT.HD</title> 
            <link>plugin://plugin.video.f4mTester/?url=http://iptvpro.vision-new.org:8789/live/gowant/faojuy/1587.ts&amp;streamtype=TSDOWNLOADER&amp;name=|IT|PREMIUM.SPORT.HD</link> 
        </item> 
          <item> 
            <title>PREMIUM_FOX_SPORT</title> 
            <link>plugin://plugin.video.f4mTester/?url=http://iptvpro.vision-new.org:8789/live/gowant/faojuy/15.ts&amp;streamtype=TSDOWNLOADER&amp;name=PREMIUM_FOX_SPORT</link> 
        </item> 
          <item> 
            <title>PREMIUM_EUROSPORT-1</title> 
            <link>plugin://plugin.video.f4mTester/?url=http://iptvpro.vision-new.org:8789/live/gowant/faojuy/13.ts&amp;streamtype=TSDOWNLOADER&amp;name=PREMIUM_EUROSPORT-1</link> 
        </item> 
          <item> 
            <title>PREMIUM_EUROSPORT-2</title> 
            <link>plugin://plugin.video.f4mTester/?url=http://iptvpro.vision-new.org:8789/live/gowant/faojuy/14.ts&amp;streamtype=TSDOWNLOADER&amp;name=PREMIUM_EUROSPORT-2</link> 
        </item> 
          <item> 
            <title>|IT|PREMIUM.CALCIO.1</title> 
            <link>plugin://plugin.video.f4mTester/?url=http://iptvpro.vision-new.org:8789/live/gowant/faojuy/6.ts&amp;streamtype=TSDOWNLOADER&amp;name=|IT|PREMIUM.CALCIO.1</link> 
        </item> 
          <item> 
            <title>PREMIUM-CALCIO-2</title> 
            <link>plugin://plugin.video.f4mTester/?url=http://iptvpro.vision-new.org:8789/live/gowant/faojuy/7.ts&amp;streamtype=TSDOWNLOADER&amp;name=PREMIUM-CALCIO-2</link> 
        </item> 
          <item> 
            <title>PREMIUM-CALCIO-3</title> 
            <link>plugin://plugin.video.f4mTester/?url=http://iptvpro.vision-new.org:8789/live/gowant/faojuy/8.ts&amp;streamtype=TSDOWNLOADER&amp;name=PREMIUM-CALCIO-3</link> 
        </item> 
          <item> 
            <title>|IT|PREMIUM.CALCIO.4</title> 
            <link>plugin://plugin.video.f4mTester/?url=http://iptvpro.vision-new.org:8789/live/gowant/faojuy/9.ts&amp;streamtype=TSDOWNLOADER&amp;name=|IT|PREMIUM.CALCIO.4</link> 
        </item> 
          <item> 
            <title>|IT|PREMIUM.CALCIO.5</title> 
            <link>plugin://plugin.video.f4mTester/?url=http://iptvpro.vision-new.org:8789/live/gowant/faojuy/397.ts&amp;streamtype=TSDOWNLOADER&amp;name=|IT|PREMIUM.CALCIO.5</link> 
        </item> 
          <item> 
            <title>|IT|PREMIUM.CALCIO.6</title> 
            <link>plugin://plugin.video.f4mTester/?url=http://iptvpro.vision-new.org:8789/live/gowant/faojuy/398.ts&amp;streamtype=TSDOWNLOADER&amp;name=|IT|PREMIUM.CALCIO.6</link> 
        </item> 
          <item> 
            <title>|IT|PREMIUM.CALCIO.7</title> 
            <link>plugin://plugin.video.f4mTester/?url=http://iptvpro.vision-new.org:8789/live/gowant/faojuy/399.ts&amp;streamtype=TSDOWNLOADER&amp;name=|IT|PREMIUM.CALCIO.7</link> 
        </item> 
          <item> 
            <title>|IT|PREMIUM.CALCIO.2</title> 
            <link>plugin://plugin.video.f4mTester/?url=http://iptvpro.vision-new.org:8789/live/gowant/faojuy/3578.ts&amp;streamtype=TSDOWNLOADER&amp;name=|IT|PREMIUM.CALCIO.2</link> 
        </item> 
          <item> 
            <title>|IT|PREMIUM.CALCIO.3</title> 
            <link>plugin://plugin.video.f4mTester/?url=http://iptvpro.vision-new.org:8789/live/gowant/faojuy/3590.ts&amp;streamtype=TSDOWNLOADER&amp;name=|IT|PREMIUM.CALCIO.3</link> 
        </item> 
  
   
