
<?xml version="1.0" encoding="utf-8" standalone="yes"?>


<item>       
<title>     [COLOR blue]  UPDATE 06-11-2017[/COLOR]     </title>
<link>http://Ignoreme</link>
<externallink></externallink>
<thumbnail>http://i.cubeupload.com/0hw4LW.png</thumbnail>
<fanart>http://i.imgur.com/cP0kZuH.jpg</fanart>
</item>


  
 


 
 
          <item> 
            <title>A&amp;E FFHD US</title> 
            <link>plugin://plugin.video.f4mTester/?url=http://portal.geniptv.com:8080/live/7hMtyUkelT/NOIhI9yvkL/7593.ts&amp;streamtype=TSDOWNLOADER&amp;name=A&amp;E FFHD US</link> 
        </item> 
          <item> 
            <title>A&amp;E HD US</title> 
            <link>plugin://plugin.video.f4mTester/?url=http://portal.geniptv.com:8080/live/7hMtyUkelT/NOIhI9yvkL/550.ts&amp;streamtype=TSDOWNLOADER&amp;name=A&amp;E HD US</link> 
        </item> 
          <item> 
            <title>A&amp;E TV HD US</title> 
            <link>plugin://plugin.video.f4mTester/?url=http://portal.geniptv.com:8080/live/7hMtyUkelT/NOIhI9yvkL/7771.ts&amp;streamtype=TSDOWNLOADER&amp;name=A&amp;E TV HD US</link> 
        </item> 
          <item> 
            <title>ABC FHD US</title> 
            <link>plugin://plugin.video.f4mTester/?url=http://portal.geniptv.com:8080/live/7hMtyUkelT/NOIhI9yvkL/7592.ts&amp;streamtype=TSDOWNLOADER&amp;name=ABC FHD US</link> 
        </item> 
          <item> 
            <title>ABC HD US</title> 
            <link>plugin://plugin.video.f4mTester/?url=http://portal.geniptv.com:8080/live/7hMtyUkelT/NOIhI9yvkL/539.ts&amp;streamtype=TSDOWNLOADER&amp;name=ABC HD US</link> 
        </item> 
          <item> 
            <title>ABC News HD US</title> 
            <link>plugin://plugin.video.f4mTester/?url=http://portal.geniptv.com:8080/live/7hMtyUkelT/NOIhI9yvkL/540.ts&amp;streamtype=TSDOWNLOADER&amp;name=ABC News HD US</link> 
        </item> 
          <item> 
            <title>ABC Spark FHD US</title> 
            <link>plugin://plugin.video.f4mTester/?url=http://portal.geniptv.com:8080/live/7hMtyUkelT/NOIhI9yvkL/7591.ts&amp;streamtype=TSDOWNLOADER&amp;name=ABC Spark FHD US</link> 
        </item> 
          <item> 
            <title>AFN Spectrum HD US</title> 
            <link>plugin://plugin.video.f4mTester/?url=http://portal.geniptv.com:8080/live/7hMtyUkelT/NOIhI9yvkL/7726.ts&amp;streamtype=TSDOWNLOADER&amp;name=AFN Spectrum HD US</link> 
        </item> 
          <item> 
            <title>AFN Sport 1 US</title> 
            <link>plugin://plugin.video.f4mTester/?url=http://portal.geniptv.com:8080/live/7hMtyUkelT/NOIhI9yvkL/1136.ts&amp;streamtype=TSDOWNLOADER&amp;name=AFN Sport 1 US</link> 
        </item> 
          <item> 
            <title>AFN Sport 2 US</title> 
            <link>plugin://plugin.video.f4mTester/?url=http://portal.geniptv.com:8080/live/7hMtyUkelT/NOIhI9yvkL/1135.ts&amp;streamtype=TSDOWNLOADER&amp;name=AFN Sport 2 US</link> 
        </item> 
          <item> 
            <title>AFN Sports HD US</title> 
            <link>plugin://plugin.video.f4mTester/?url=#EXTINF:-1,AFN Sports&amp;streamtype=TSDOWNLOADER&amp;name=AFN Sports HD US</link> 
        </item> 
          <item> 
            <title></title> 
            <link>plugin://plugin.video.f4mTester/?url=http://portal.geniptv.com:8080/live/7hMtyUkelT/NOIhI9yvkL/7725.ts&amp;streamtype=TSDOWNLOADER&amp;name=</link> 
        </item> 
          <item> 
            <title>AMC FHD US</title> 
            <link>plugin://plugin.video.f4mTester/?url=http://portal.geniptv.com:8080/live/7hMtyUkelT/NOIhI9yvkL/7590.ts&amp;streamtype=TSDOWNLOADER&amp;name=AMC FHD US</link> 
        </item> 
          <item> 
            <title>AMC HD US</title> 
            <link>plugin://plugin.video.f4mTester/?url=http://portal.geniptv.com:8080/live/7hMtyUkelT/NOIhI9yvkL/521.ts&amp;streamtype=TSDOWNLOADER&amp;name=AMC HD US</link> 
        </item> 
          <item> 
            <title>AMC US</title> 
            <link>plugin://plugin.video.f4mTester/?url=http://portal.geniptv.com:8080/live/7hMtyUkelT/NOIhI9yvkL/7792.ts&amp;streamtype=TSDOWNLOADER&amp;name=AMC US</link> 
        </item> 
          <item> 
            <title>Amazing Discoveries HD US</title> 
            <link>plugin://plugin.video.f4mTester/?url=http://portal.geniptv.com:8080/live/7hMtyUkelT/NOIhI9yvkL/551.ts&amp;streamtype=TSDOWNLOADER&amp;name=Amazing Discoveries HD US</link> 
        </item> 
          <item> 
            <title>American Heroes HD US</title> 
            <link>plugin://plugin.video.f4mTester/?url=http://portal.geniptv.com:8080/live/7hMtyUkelT/NOIhI9yvkL/7718.ts&amp;streamtype=TSDOWNLOADER&amp;name=American Heroes HD US</link> 
        </item> 
          <item> 
            <title>Animal Planet FHD US</title> 
            <link>plugin://plugin.video.f4mTester/?url=http://portal.geniptv.com:8080/live/7hMtyUkelT/NOIhI9yvkL/7589.ts&amp;streamtype=TSDOWNLOADER&amp;name=Animal Planet FHD US</link> 
        </item> 
          <item> 
            <title>Animal Planet HD US</title> 
            <link>plugin://plugin.video.f4mTester/?url=http://portal.geniptv.com:8080/live/7hMtyUkelT/NOIhI9yvkL/563.ts&amp;streamtype=TSDOWNLOADER&amp;name=Animal Planet HD US</link> 
        </item> 
          <item> 
            <title>Animal Planet US</title> 
            <link>plugin://plugin.video.f4mTester/?url=http://portal.geniptv.com:8080/live/7hMtyUkelT/NOIhI9yvkL/7791.ts&amp;streamtype=TSDOWNLOADER&amp;name=Animal Planet US</link> 
        </item> 
          <item> 
            <title>BBC America FHD US</title> 
            <link>plugin://plugin.video.f4mTester/?url=http://portal.geniptv.com:8080/live/7hMtyUkelT/NOIhI9yvkL/7588.ts&amp;streamtype=TSDOWNLOADER&amp;name=BBC America FHD US</link> 
        </item> 
          <item> 
            <title>BET FHD US</title> 
            <link>plugin://plugin.video.f4mTester/?url=http://portal.geniptv.com:8080/live/7hMtyUkelT/NOIhI9yvkL/7587.ts&amp;streamtype=TSDOWNLOADER&amp;name=BET FHD US</link> 
        </item> 
          <item> 
            <title>BET HD US</title> 
            <link>plugin://plugin.video.f4mTester/?url=http://portal.geniptv.com:8080/live/7hMtyUkelT/NOIhI9yvkL/7770.ts&amp;streamtype=TSDOWNLOADER&amp;name=BET HD US</link> 
        </item> 
          <item> 
            <title>BYU TV US</title> 
            <link>plugin://plugin.video.f4mTester/?url=http://portal.geniptv.com:8080/live/7hMtyUkelT/NOIhI9yvkL/522.ts&amp;streamtype=TSDOWNLOADER&amp;name=BYU TV US</link> 
        </item> 
          <item> 
            <title>Big Ten Network HD US</title> 
            <link>plugin://plugin.video.f4mTester/?url=http://portal.geniptv.com:8080/live/7hMtyUkelT/NOIhI9yvkL/7724.ts&amp;streamtype=TSDOWNLOADER&amp;name=Big Ten Network HD US</link> 
        </item> 
          <item> 
            <title>Bloomberg Europe US</title> 
            <link>plugin://plugin.video.f4mTester/?url=http://portal.geniptv.com:8080/live/7hMtyUkelT/NOIhI9yvkL/503.ts&amp;streamtype=TSDOWNLOADER&amp;name=Bloomberg Europe US</link> 
        </item> 
          <item> 
            <title>Bloomberg TV 1080P HD US</title> 
            <link>plugin://plugin.video.f4mTester/?url=http://portal.geniptv.com:8080/live/7hMtyUkelT/NOIhI9yvkL/489.ts&amp;streamtype=TSDOWNLOADER&amp;name=Bloomberg TV 1080P HD US</link> 
        </item> 
          <item> 
            <title>Boomerang US</title> 
            <link>plugin://plugin.video.f4mTester/?url=http://portal.geniptv.com:8080/live/7hMtyUkelT/NOIhI9yvkL/502.ts&amp;streamtype=TSDOWNLOADER&amp;name=Boomerang US</link> 
        </item> 
          <item> 
            <title>Bravo FHD US</title> 
            <link>plugin://plugin.video.f4mTester/?url=http://portal.geniptv.com:8080/live/7hMtyUkelT/NOIhI9yvkL/7586.ts&amp;streamtype=TSDOWNLOADER&amp;name=Bravo FHD US</link> 
        </item> 
          <item> 
            <title>Bravo HD US</title> 
            <link>plugin://plugin.video.f4mTester/?url=http://portal.geniptv.com:8080/live/7hMtyUkelT/NOIhI9yvkL/541.ts&amp;streamtype=TSDOWNLOADER&amp;name=Bravo HD US</link> 
        </item> 
          <item> 
            <title>Bravo US</title> 
            <link>plugin://plugin.video.f4mTester/?url=http://portal.geniptv.com:8080/live/7hMtyUkelT/NOIhI9yvkL/7790.ts&amp;streamtype=TSDOWNLOADER&amp;name=Bravo US</link> 
        </item> 
          <item> 
            <title>C-Span 1 US</title> 
            <link>plugin://plugin.video.f4mTester/?url=http://portal.geniptv.com:8080/live/7hMtyUkelT/NOIhI9yvkL/564.ts&amp;streamtype=TSDOWNLOADER&amp;name=C-Span 1 US</link> 
        </item> 
          <item> 
            <title>C-Span 2 US</title> 
            <link>plugin://plugin.video.f4mTester/?url=http://portal.geniptv.com:8080/live/7hMtyUkelT/NOIhI9yvkL/565.ts&amp;streamtype=TSDOWNLOADER&amp;name=C-Span 2 US</link> 
        </item> 
          <item> 
            <title>C-Span 3 US</title> 
            <link>plugin://plugin.video.f4mTester/?url=http://portal.geniptv.com:8080/live/7hMtyUkelT/NOIhI9yvkL/566.ts&amp;streamtype=TSDOWNLOADER&amp;name=C-Span 3 US</link> 
        </item> 
          <item> 
            <title>CA Sportsnet 360 HD US</title> 
            <link>plugin://plugin.video.f4mTester/?url=#EXTINF:-1,CA Sports&amp;streamtype=TSDOWNLOADER&amp;name=CA Sportsnet 360 HD US</link> 
        </item> 
          <item> 
            <title></title> 
            <link>plugin://plugin.video.f4mTester/?url=http://portal.geniptv.com:8080/live/7hMtyUkelT/NOIhI9yvkL/487.ts&amp;streamtype=TSDOWNLOADER&amp;name=</link> 
        </item> 
          <item> 
            <title>CBS FHD US</title> 
            <link>plugin://plugin.video.f4mTester/?url=http://portal.geniptv.com:8080/live/7hMtyUkelT/NOIhI9yvkL/7584.ts&amp;streamtype=TSDOWNLOADER&amp;name=CBS FHD US</link> 
        </item> 
          <item> 
            <title>CBS Sports Network FHD US</title> 
            <link>plugin://plugin.video.f4mTester/?url=#EXTINF:-1,CBS Sports&amp;streamtype=TSDOWNLOADER&amp;name=CBS Sports Network FHD US</link> 
        </item> 
          <item> 
            <title></title> 
            <link>plugin://plugin.video.f4mTester/?url=http://portal.geniptv.com:8080/live/7hMtyUkelT/NOIhI9yvkL/7583.ts&amp;streamtype=TSDOWNLOADER&amp;name=</link> 
        </item> 
          <item> 
            <title>CBS US</title> 
            <link>plugin://plugin.video.f4mTester/?url=http://portal.geniptv.com:8080/live/7hMtyUkelT/NOIhI9yvkL/486.ts&amp;streamtype=TSDOWNLOADER&amp;name=CBS US</link> 
        </item> 
          <item> 
            <title>CBSN HD US</title> 
            <link>plugin://plugin.video.f4mTester/?url=http://portal.geniptv.com:8080/live/7hMtyUkelT/NOIhI9yvkL/524.ts&amp;streamtype=TSDOWNLOADER&amp;name=CBSN HD US</link> 
        </item> 
          <item> 
            <title>CNBC FHD US</title> 
            <link>plugin://plugin.video.f4mTester/?url=http://portal.geniptv.com:8080/live/7hMtyUkelT/NOIhI9yvkL/7582.ts&amp;streamtype=TSDOWNLOADER&amp;name=CNBC FHD US</link> 
        </item> 
          <item> 
            <title>CNBC US</title> 
            <link>plugin://plugin.video.f4mTester/?url=http://portal.geniptv.com:8080/live/7hMtyUkelT/NOIhI9yvkL/525.ts&amp;streamtype=TSDOWNLOADER&amp;name=CNBC US</link> 
        </item> 
          <item> 
            <title>CNN HD US</title> 
            <link>plugin://plugin.video.f4mTester/?url=http://portal.geniptv.com:8080/live/7hMtyUkelT/NOIhI9yvkL/568.ts&amp;streamtype=TSDOWNLOADER&amp;name=CNN HD US</link> 
        </item> 
          <item> 
            <title>CNN News FHD US</title> 
            <link>plugin://plugin.video.f4mTester/?url=http://portal.geniptv.com:8080/live/7hMtyUkelT/NOIhI9yvkL/7581.ts&amp;streamtype=TSDOWNLOADER&amp;name=CNN News FHD US</link> 
        </item> 
          <item> 
            <title>CSNS Sports Area Bay HD US</title> 
            <link>plugin://plugin.video.f4mTester/?url=#EXTINF:-1,CSNS Sports&amp;streamtype=TSDOWNLOADER&amp;name=CSNS Sports Area Bay HD US</link> 
        </item> 
          <item> 
            <title></title> 
            <link>plugin://plugin.video.f4mTester/?url=http://portal.geniptv.com:8080/live/7hMtyUkelT/NOIhI9yvkL/7697.ts&amp;streamtype=TSDOWNLOADER&amp;name=</link> 
        </item> 
          <item> 
            <title>CSNS Sports Boston HD US</title> 
            <link>plugin://plugin.video.f4mTester/?url=#EXTINF:-1,CSNS Sports&amp;streamtype=TSDOWNLOADER&amp;name=CSNS Sports Boston HD US</link> 
        </item> 
          <item> 
            <title></title> 
            <link>plugin://plugin.video.f4mTester/?url=http://portal.geniptv.com:8080/live/7hMtyUkelT/NOIhI9yvkL/7699.ts&amp;streamtype=TSDOWNLOADER&amp;name=</link> 
        </item> 
          <item> 
            <title>CSNS Sports California HD US</title> 
            <link>plugin://plugin.video.f4mTester/?url=#EXTINF:-1,CSNS Sports&amp;streamtype=TSDOWNLOADER&amp;name=CSNS Sports California HD US</link> 
        </item> 
          <item> 
            <title></title> 
            <link>plugin://plugin.video.f4mTester/?url=http://portal.geniptv.com:8080/live/7hMtyUkelT/NOIhI9yvkL/7696.ts&amp;streamtype=TSDOWNLOADER&amp;name=</link> 
        </item> 
          <item> 
            <title>CSNS Sports Chicago HD US</title> 
            <link>plugin://plugin.video.f4mTester/?url=#EXTINF:-1,CSNS Sports&amp;streamtype=TSDOWNLOADER&amp;name=CSNS Sports Chicago HD US</link> 
        </item> 
          <item> 
            <title></title> 
            <link>plugin://plugin.video.f4mTester/?url=http://portal.geniptv.com:8080/live/7hMtyUkelT/NOIhI9yvkL/7698.ts&amp;streamtype=TSDOWNLOADER&amp;name=</link> 
        </item> 
          <item> 
            <title>CSNS Sports Washington HD US</title> 
            <link>plugin://plugin.video.f4mTester/?url=#EXTINF:-1,CSNS Sports&amp;streamtype=TSDOWNLOADER&amp;name=CSNS Sports Washington HD US</link> 
        </item> 
          <item> 
            <title></title> 
            <link>plugin://plugin.video.f4mTester/?url=http://portal.geniptv.com:8080/live/7hMtyUkelT/NOIhI9yvkL/7695.ts&amp;streamtype=TSDOWNLOADER&amp;name=</link> 
        </item> 
          <item> 
            <title>CW HD US</title> 
            <link>plugin://plugin.video.f4mTester/?url=http://portal.geniptv.com:8080/live/7hMtyUkelT/NOIhI9yvkL/543.ts&amp;streamtype=TSDOWNLOADER&amp;name=CW HD US</link> 
        </item> 
          <item> 
            <title>CW US</title> 
            <link>plugin://plugin.video.f4mTester/?url=http://portal.geniptv.com:8080/live/7hMtyUkelT/NOIhI9yvkL/7777.ts&amp;streamtype=TSDOWNLOADER&amp;name=CW US</link> 
        </item> 
          <item> 
            <title>CW11 US</title> 
            <link>plugin://plugin.video.f4mTester/?url=http://portal.geniptv.com:8080/live/7hMtyUkelT/NOIhI9yvkL/500.ts&amp;streamtype=TSDOWNLOADER&amp;name=CW11 US</link> 
        </item> 
          <item> 
            <title>Cable News Network HD US</title> 
            <link>plugin://plugin.video.f4mTester/?url=http://portal.geniptv.com:8080/live/7hMtyUkelT/NOIhI9yvkL/7769.ts&amp;streamtype=TSDOWNLOADER&amp;name=Cable News Network HD US</link> 
        </item> 
          <item> 
            <title>Cartoon Network FHD US</title> 
            <link>plugin://plugin.video.f4mTester/?url=http://portal.geniptv.com:8080/live/7hMtyUkelT/NOIhI9yvkL/7585.ts&amp;streamtype=TSDOWNLOADER&amp;name=Cartoon Network FHD US</link> 
        </item> 
          <item> 
            <title>Cartoon Network US</title> 
            <link>plugin://plugin.video.f4mTester/?url=http://portal.geniptv.com:8080/live/7hMtyUkelT/NOIhI9yvkL/523.ts&amp;streamtype=TSDOWNLOADER&amp;name=Cartoon Network US</link> 
        </item> 
          <item> 
            <title>Chiller HD US</title> 
            <link>plugin://plugin.video.f4mTester/?url=http://portal.geniptv.com:8080/live/7hMtyUkelT/NOIhI9yvkL/7717.ts&amp;streamtype=TSDOWNLOADER&amp;name=Chiller HD US</link> 
        </item> 
          <item> 
            <title>CineMax 5 StarMax US</title> 
            <link>plugin://plugin.video.f4mTester/?url=http://portal.geniptv.com:8080/live/7hMtyUkelT/NOIhI9yvkL/507.ts&amp;streamtype=TSDOWNLOADER&amp;name=CineMax 5 StarMax US</link> 
        </item> 
          <item> 
            <title>CineMax Action HD US</title> 
            <link>plugin://plugin.video.f4mTester/?url=http://portal.geniptv.com:8080/live/7hMtyUkelT/NOIhI9yvkL/567.ts&amp;streamtype=TSDOWNLOADER&amp;name=CineMax Action HD US</link> 
        </item> 
          <item> 
            <title>CineMax ActionMax East US</title> 
            <link>plugin://plugin.video.f4mTester/?url=http://portal.geniptv.com:8080/live/7hMtyUkelT/NOIhI9yvkL/508.ts&amp;streamtype=TSDOWNLOADER&amp;name=CineMax ActionMax East US</link> 
        </item> 
          <item> 
            <title>CineMax East US</title> 
            <link>plugin://plugin.video.f4mTester/?url=http://portal.geniptv.com:8080/live/7hMtyUkelT/NOIhI9yvkL/509.ts&amp;streamtype=TSDOWNLOADER&amp;name=CineMax East US</link> 
        </item> 
          <item> 
            <title>CineMax MoreMax US</title> 
            <link>plugin://plugin.video.f4mTester/?url=http://portal.geniptv.com:8080/live/7hMtyUkelT/NOIhI9yvkL/501.ts&amp;streamtype=TSDOWNLOADER&amp;name=CineMax MoreMax US</link> 
        </item> 
          <item> 
            <title>Cinemax Action US</title> 
            <link>plugin://plugin.video.f4mTester/?url=http://portal.geniptv.com:8080/live/7hMtyUkelT/NOIhI9yvkL/7789.ts&amp;streamtype=TSDOWNLOADER&amp;name=Cinemax Action US</link> 
        </item> 
          <item> 
            <title>Cinemax More HD US</title> 
            <link>plugin://plugin.video.f4mTester/?url=http://portal.geniptv.com:8080/live/7hMtyUkelT/NOIhI9yvkL/7768.ts&amp;streamtype=TSDOWNLOADER&amp;name=Cinemax More HD US</link> 
        </item> 
          <item> 
            <title>City TV HD US</title> 
            <link>plugin://plugin.video.f4mTester/?url=http://portal.geniptv.com:8080/live/7hMtyUkelT/NOIhI9yvkL/7723.ts&amp;streamtype=TSDOWNLOADER&amp;name=City TV HD US</link> 
        </item> 
          <item> 
            <title>Comedy Central FHD US</title> 
            <link>plugin://plugin.video.f4mTester/?url=http://portal.geniptv.com:8080/live/7hMtyUkelT/NOIhI9yvkL/542.ts&amp;streamtype=TSDOWNLOADER&amp;name=Comedy Central FHD US</link> 
        </item> 
          <item> 
            <title>Comedy Central HD US</title> 
            <link>plugin://plugin.video.f4mTester/?url=http://portal.geniptv.com:8080/live/7hMtyUkelT/NOIhI9yvkL/7595.ts&amp;streamtype=TSDOWNLOADER&amp;name=Comedy Central HD US</link> 
        </item> 
          <item> 
            <title>Comedy Central US</title> 
            <link>plugin://plugin.video.f4mTester/?url=http://portal.geniptv.com:8080/live/7hMtyUkelT/NOIhI9yvkL/7788.ts&amp;streamtype=TSDOWNLOADER&amp;name=Comedy Central US</link> 
        </item> 
          <item> 
            <title>DIY Network HD US</title> 
            <link>plugin://plugin.video.f4mTester/?url=http://portal.geniptv.com:8080/live/7hMtyUkelT/NOIhI9yvkL/7728.ts&amp;streamtype=TSDOWNLOADER&amp;name=DIY Network HD US</link> 
        </item> 
          <item> 
            <title>DIY Network US</title> 
            <link>plugin://plugin.video.f4mTester/?url=http://portal.geniptv.com:8080/live/7hMtyUkelT/NOIhI9yvkL/482.ts&amp;streamtype=TSDOWNLOADER&amp;name=DIY Network US</link> 
        </item> 
          <item> 
            <title>DW US</title> 
            <link>plugin://plugin.video.f4mTester/?url=http://portal.geniptv.com:8080/live/7hMtyUkelT/NOIhI9yvkL/528.ts&amp;streamtype=TSDOWNLOADER&amp;name=DW US</link> 
        </item> 
          <item> 
            <title>Destination America HD US</title> 
            <link>plugin://plugin.video.f4mTester/?url=http://portal.geniptv.com:8080/live/7hMtyUkelT/NOIhI9yvkL/7716.ts&amp;streamtype=TSDOWNLOADER&amp;name=Destination America HD US</link> 
        </item> 
          <item> 
            <title>Discovery Channel CA FHD US</title> 
            <link>plugin://plugin.video.f4mTester/?url=http://portal.geniptv.com:8080/live/7hMtyUkelT/NOIhI9yvkL/7580.ts&amp;streamtype=TSDOWNLOADER&amp;name=Discovery Channel CA FHD US</link> 
        </item> 
          <item> 
            <title>Discovery Channel FHD US</title> 
            <link>plugin://plugin.video.f4mTester/?url=http://portal.geniptv.com:8080/live/7hMtyUkelT/NOIhI9yvkL/7579.ts&amp;streamtype=TSDOWNLOADER&amp;name=Discovery Channel FHD US</link> 
        </item> 
          <item> 
            <title>Discovery Channel HD US</title> 
            <link>plugin://plugin.video.f4mTester/?url=http://portal.geniptv.com:8080/live/7hMtyUkelT/NOIhI9yvkL/7767.ts&amp;streamtype=TSDOWNLOADER&amp;name=Discovery Channel HD US</link> 
        </item> 
          <item> 
            <title>Discovery HD Showcase US</title> 
            <link>plugin://plugin.video.f4mTester/?url=http://portal.geniptv.com:8080/live/7hMtyUkelT/NOIhI9yvkL/499.ts&amp;streamtype=TSDOWNLOADER&amp;name=Discovery HD Showcase US</link> 
        </item> 
          <item> 
            <title>Discovery HD US</title> 
            <link>plugin://plugin.video.f4mTester/?url=http://portal.geniptv.com:8080/live/7hMtyUkelT/NOIhI9yvkL/526.ts&amp;streamtype=TSDOWNLOADER&amp;name=Discovery HD US</link> 
        </item> 
          <item> 
            <title>Discovery Science HD US</title> 
            <link>plugin://plugin.video.f4mTester/?url=http://portal.geniptv.com:8080/live/7hMtyUkelT/NOIhI9yvkL/510.ts&amp;streamtype=TSDOWNLOADER&amp;name=Discovery Science HD US</link> 
        </item> 
          <item> 
            <title>Discovery Science US</title> 
            <link>plugin://plugin.video.f4mTester/?url=http://portal.geniptv.com:8080/live/7hMtyUkelT/NOIhI9yvkL/7774.ts&amp;streamtype=TSDOWNLOADER&amp;name=Discovery Science US</link> 
        </item> 
          <item> 
            <title>Discovery Showcase HD US</title> 
            <link>plugin://plugin.video.f4mTester/?url=http://portal.geniptv.com:8080/live/7hMtyUkelT/NOIhI9yvkL/7689.ts&amp;streamtype=TSDOWNLOADER&amp;name=Discovery Showcase HD US</link> 
        </item> 
          <item> 
            <title>Discovery Velocity US</title> 
            <link>plugin://plugin.video.f4mTester/?url=http://portal.geniptv.com:8080/live/7hMtyUkelT/NOIhI9yvkL/527.ts&amp;streamtype=TSDOWNLOADER&amp;name=Discovery Velocity US</link> 
        </item> 
          <item> 
            <title>Disney Channel FHD US</title> 
            <link>plugin://plugin.video.f4mTester/?url=http://portal.geniptv.com:8080/live/7hMtyUkelT/NOIhI9yvkL/7578.ts&amp;streamtype=TSDOWNLOADER&amp;name=Disney Channel FHD US</link> 
        </item> 
          <item> 
            <title>Disney Channel HD US</title> 
            <link>plugin://plugin.video.f4mTester/?url=http://portal.geniptv.com:8080/live/7hMtyUkelT/NOIhI9yvkL/7766.ts&amp;streamtype=TSDOWNLOADER&amp;name=Disney Channel HD US</link> 
        </item> 
          <item> 
            <title>Disney XD FHD US</title> 
            <link>plugin://plugin.video.f4mTester/?url=http://portal.geniptv.com:8080/live/7hMtyUkelT/NOIhI9yvkL/7577.ts&amp;streamtype=TSDOWNLOADER&amp;name=Disney XD FHD US</link> 
        </item> 
          <item> 
            <title>Disney XD HD US</title> 
            <link>plugin://plugin.video.f4mTester/?url=http://portal.geniptv.com:8080/live/7hMtyUkelT/NOIhI9yvkL/7765.ts&amp;streamtype=TSDOWNLOADER&amp;name=Disney XD HD US</link> 
        </item> 
          <item> 
            <title>E! Entertainment HD US</title> 
            <link>plugin://plugin.video.f4mTester/?url=http://portal.geniptv.com:8080/live/7hMtyUkelT/NOIhI9yvkL/7764.ts&amp;streamtype=TSDOWNLOADER&amp;name=E! Entertainment HD US</link> 
        </item> 
          <item> 
            <title>E! FHD US</title> 
            <link>plugin://plugin.video.f4mTester/?url=http://portal.geniptv.com:8080/live/7hMtyUkelT/NOIhI9yvkL/7576.ts&amp;streamtype=TSDOWNLOADER&amp;name=E! FHD US</link> 
        </item> 
          <item> 
            <title>ESPN 1 HD US</title> 
            <link>plugin://plugin.video.f4mTester/?url=http://portal.geniptv.com:8080/live/7hMtyUkelT/NOIhI9yvkL/7763.ts&amp;streamtype=TSDOWNLOADER&amp;name=ESPN 1 HD US</link> 
        </item> 
          <item> 
            <title>ESPN 1 US</title> 
            <link>plugin://plugin.video.f4mTester/?url=http://portal.geniptv.com:8080/live/7hMtyUkelT/NOIhI9yvkL/552.ts&amp;streamtype=TSDOWNLOADER&amp;name=ESPN 1 US</link> 
        </item> 
          <item> 
            <title>ESPN 2 FHD US</title> 
            <link>plugin://plugin.video.f4mTester/?url=http://portal.geniptv.com:8080/live/7hMtyUkelT/NOIhI9yvkL/569.ts&amp;streamtype=TSDOWNLOADER&amp;name=ESPN 2 FHD US</link> 
        </item> 
          <item> 
            <title>ESPN 2 HD US</title> 
            <link>plugin://plugin.video.f4mTester/?url=http://portal.geniptv.com:8080/live/7hMtyUkelT/NOIhI9yvkL/7594.ts&amp;streamtype=TSDOWNLOADER&amp;name=ESPN 2 HD US</link> 
        </item> 
          <item> 
            <title>ESPN 2 US</title> 
            <link>plugin://plugin.video.f4mTester/?url=http://portal.geniptv.com:8080/live/7hMtyUkelT/NOIhI9yvkL/7787.ts&amp;streamtype=TSDOWNLOADER&amp;name=ESPN 2 US</link> 
        </item> 
          <item> 
            <title>ESPN HD US</title> 
            <link>plugin://plugin.video.f4mTester/?url=http://portal.geniptv.com:8080/live/7hMtyUkelT/NOIhI9yvkL/544.ts&amp;streamtype=TSDOWNLOADER&amp;name=ESPN HD US</link> 
        </item> 
          <item> 
            <title>ESPN New HD US</title> 
            <link>plugin://plugin.video.f4mTester/?url=http://portal.geniptv.com:8080/live/7hMtyUkelT/NOIhI9yvkL/7761.ts&amp;streamtype=TSDOWNLOADER&amp;name=ESPN New HD US</link> 
        </item> 
          <item> 
            <title>ESPN U HD US</title> 
            <link>plugin://plugin.video.f4mTester/?url=http://portal.geniptv.com:8080/live/7hMtyUkelT/NOIhI9yvkL/7762.ts&amp;streamtype=TSDOWNLOADER&amp;name=ESPN U HD US</link> 
        </item> 
          <item> 
            <title>El Rey Network FHD US</title> 
            <link>plugin://plugin.video.f4mTester/?url=http://portal.geniptv.com:8080/live/7hMtyUkelT/NOIhI9yvkL/7575.ts&amp;streamtype=TSDOWNLOADER&amp;name=El Rey Network FHD US</link> 
        </item> 
          <item> 
            <title>El Rey Network HD US</title> 
            <link>plugin://plugin.video.f4mTester/?url=http://portal.geniptv.com:8080/live/7hMtyUkelT/NOIhI9yvkL/7715.ts&amp;streamtype=TSDOWNLOADER&amp;name=El Rey Network HD US</link> 
        </item> 
          <item> 
            <title>Eleven Sports Network HD US</title> 
            <link>plugin://plugin.video.f4mTester/?url=#EXTINF:-1,Eleven Sports&amp;streamtype=TSDOWNLOADER&amp;name=Eleven Sports Network HD US</link> 
        </item> 
          <item> 
            <title></title> 
            <link>plugin://plugin.video.f4mTester/?url=http://portal.geniptv.com:8080/live/7hMtyUkelT/NOIhI9yvkL/7714.ts&amp;streamtype=TSDOWNLOADER&amp;name=</link> 
        </item> 
          <item> 
            <title>FNTSY Network HD US</title> 
            <link>plugin://plugin.video.f4mTester/?url=http://portal.geniptv.com:8080/live/7hMtyUkelT/NOIhI9yvkL/7721.ts&amp;streamtype=TSDOWNLOADER&amp;name=FNTSY Network HD US</link> 
        </item> 
          <item> 
            <title>FOX 43 US</title> 
            <link>plugin://plugin.video.f4mTester/?url=http://portal.geniptv.com:8080/live/7hMtyUkelT/NOIhI9yvkL/570.ts&amp;streamtype=TSDOWNLOADER&amp;name=FOX 43 US</link> 
        </item> 
          <item> 
            <title>FS1 US</title> 
            <link>plugin://plugin.video.f4mTester/?url=http://portal.geniptv.com:8080/live/7hMtyUkelT/NOIhI9yvkL/1137.ts&amp;streamtype=TSDOWNLOADER&amp;name=FS1 US</link> 
        </item> 
          <item> 
            <title>FX FHD US</title> 
            <link>plugin://plugin.video.f4mTester/?url=http://portal.geniptv.com:8080/live/7hMtyUkelT/NOIhI9yvkL/7569.ts&amp;streamtype=TSDOWNLOADER&amp;name=FX FHD US</link> 
        </item> 
          <item> 
            <title>FX HD US</title> 
            <link>plugin://plugin.video.f4mTester/?url=http://portal.geniptv.com:8080/live/7hMtyUkelT/NOIhI9yvkL/513.ts&amp;streamtype=TSDOWNLOADER&amp;name=FX HD US</link> 
        </item> 
          <item> 
            <title>FX US</title> 
            <link>plugin://plugin.video.f4mTester/?url=http://portal.geniptv.com:8080/live/7hMtyUkelT/NOIhI9yvkL/7784.ts&amp;streamtype=TSDOWNLOADER&amp;name=FX US</link> 
        </item> 
          <item> 
            <title>FXX FHD US</title> 
            <link>plugin://plugin.video.f4mTester/?url=http://portal.geniptv.com:8080/live/7hMtyUkelT/NOIhI9yvkL/7568.ts&amp;streamtype=TSDOWNLOADER&amp;name=FXX FHD US</link> 
        </item> 
          <item> 
            <title>FXX HD US</title> 
            <link>plugin://plugin.video.f4mTester/?url=http://portal.geniptv.com:8080/live/7hMtyUkelT/NOIhI9yvkL/7722.ts&amp;streamtype=TSDOWNLOADER&amp;name=FXX HD US</link> 
        </item> 
          <item> 
            <title>Family FHD US</title> 
            <link>plugin://plugin.video.f4mTester/?url=http://portal.geniptv.com:8080/live/7hMtyUkelT/NOIhI9yvkL/7574.ts&amp;streamtype=TSDOWNLOADER&amp;name=Family FHD US</link> 
        </item> 
          <item> 
            <title>Fashion One HD US</title> 
            <link>plugin://plugin.video.f4mTester/?url=http://portal.geniptv.com:8080/live/7hMtyUkelT/NOIhI9yvkL/498.ts&amp;streamtype=TSDOWNLOADER&amp;name=Fashion One HD US</link> 
        </item> 
          <item> 
            <title>Fight HD US</title> 
            <link>plugin://plugin.video.f4mTester/?url=http://portal.geniptv.com:8080/live/7hMtyUkelT/NOIhI9yvkL/529.ts&amp;streamtype=TSDOWNLOADER&amp;name=Fight HD US</link> 
        </item> 
          <item> 
            <title>Fight Network HD US</title> 
            <link>plugin://plugin.video.f4mTester/?url=http://portal.geniptv.com:8080/live/7hMtyUkelT/NOIhI9yvkL/7702.ts&amp;streamtype=TSDOWNLOADER&amp;name=Fight Network HD US</link> 
        </item> 
          <item> 
            <title>Fight Sport US</title> 
            <link>plugin://plugin.video.f4mTester/?url=http://portal.geniptv.com:8080/live/7hMtyUkelT/NOIhI9yvkL/584.ts&amp;streamtype=TSDOWNLOADER&amp;name=Fight Sport US</link> 
        </item> 
          <item> 
            <title>Fine Living US</title> 
            <link>plugin://plugin.video.f4mTester/?url=http://portal.geniptv.com:8080/live/7hMtyUkelT/NOIhI9yvkL/497.ts&amp;streamtype=TSDOWNLOADER&amp;name=Fine Living US</link> 
        </item> 
          <item> 
            <title>Food Network HD US</title> 
            <link>plugin://plugin.video.f4mTester/?url=http://portal.geniptv.com:8080/live/7hMtyUkelT/NOIhI9yvkL/511.ts&amp;streamtype=TSDOWNLOADER&amp;name=Food Network HD US</link> 
        </item> 
          <item> 
            <title>Food Network US</title> 
            <link>plugin://plugin.video.f4mTester/?url=http://portal.geniptv.com:8080/live/7hMtyUkelT/NOIhI9yvkL/7783.ts&amp;streamtype=TSDOWNLOADER&amp;name=Food Network US</link> 
        </item> 
          <item> 
            <title>Fox College Sports Atlantic HD US</title> 
            <link>plugin://plugin.video.f4mTester/?url=#EXTINF:-1,Fox College Sports&amp;streamtype=TSDOWNLOADER&amp;name=Fox College Sports Atlantic HD US</link> 
        </item> 
          <item> 
            <title></title> 
            <link>plugin://plugin.video.f4mTester/?url=http://portal.geniptv.com:8080/live/7hMtyUkelT/NOIhI9yvkL/7751.ts&amp;streamtype=TSDOWNLOADER&amp;name=</link> 
        </item> 
          <item> 
            <title>Fox Deportes HD US</title> 
            <link>plugin://plugin.video.f4mTester/?url=http://portal.geniptv.com:8080/live/7hMtyUkelT/NOIhI9yvkL/7750.ts&amp;streamtype=TSDOWNLOADER&amp;name=Fox Deportes HD US</link> 
        </item> 
          <item> 
            <title>Fox FHD US</title> 
            <link>plugin://plugin.video.f4mTester/?url=http://portal.geniptv.com:8080/live/7hMtyUkelT/NOIhI9yvkL/7573.ts&amp;streamtype=TSDOWNLOADER&amp;name=Fox FHD US</link> 
        </item> 
          <item> 
            <title>Fox HD US</title> 
            <link>plugin://plugin.video.f4mTester/?url=http://portal.geniptv.com:8080/live/7hMtyUkelT/NOIhI9yvkL/512.ts&amp;streamtype=TSDOWNLOADER&amp;name=Fox HD US</link> 
        </item> 
          <item> 
            <title>Fox News FHD US</title> 
            <link>plugin://plugin.video.f4mTester/?url=http://portal.geniptv.com:8080/live/7hMtyUkelT/NOIhI9yvkL/7572.ts&amp;streamtype=TSDOWNLOADER&amp;name=Fox News FHD US</link> 
        </item> 
          <item> 
            <title>Fox News HD US</title> 
            <link>plugin://plugin.video.f4mTester/?url=http://portal.geniptv.com:8080/live/7hMtyUkelT/NOIhI9yvkL/545.ts&amp;streamtype=TSDOWNLOADER&amp;name=Fox News HD US</link> 
        </item> 
          <item> 
            <title>Fox Soccer Plus HD US</title> 
            <link>plugin://plugin.video.f4mTester/?url=http://portal.geniptv.com:8080/live/7hMtyUkelT/NOIhI9yvkL/6206.ts&amp;streamtype=TSDOWNLOADER&amp;name=Fox Soccer Plus HD US</link> 
        </item> 
          <item> 
            <title>Fox Soccer Plus US</title> 
            <link>plugin://plugin.video.f4mTester/?url=http://portal.geniptv.com:8080/live/7hMtyUkelT/NOIhI9yvkL/7785.ts&amp;streamtype=TSDOWNLOADER&amp;name=Fox Soccer Plus US</link> 
        </item> 
          <item> 
            <title>Fox Sports 1 FHD US</title> 
            <link>plugin://plugin.video.f4mTester/?url=#EXTINF:-1,Fox Sports&amp;streamtype=TSDOWNLOADER&amp;name=Fox Sports 1 FHD US</link> 
        </item> 
          <item> 
            <title></title> 
            <link>plugin://plugin.video.f4mTester/?url=http://portal.geniptv.com:8080/live/7hMtyUkelT/NOIhI9yvkL/7571.ts&amp;streamtype=TSDOWNLOADER&amp;name=</link> 
        </item> 
          <item> 
            <title>Fox Sports 1 HD US</title> 
            <link>plugin://plugin.video.f4mTester/?url=#EXTINF:-1,Fox Sports&amp;streamtype=TSDOWNLOADER&amp;name=Fox Sports 1 HD US</link> 
        </item> 
          <item> 
            <title></title> 
            <link>plugin://plugin.video.f4mTester/?url=http://portal.geniptv.com:8080/live/7hMtyUkelT/NOIhI9yvkL/553.ts&amp;streamtype=TSDOWNLOADER&amp;name=</link> 
        </item> 
          <item> 
            <title>Fox Sports 1 US</title> 
            <link>plugin://plugin.video.f4mTester/?url=#EXTINF:-1,Fox Sports&amp;streamtype=TSDOWNLOADER&amp;name=Fox Sports 1 US</link> 
        </item> 
          <item> 
            <title></title> 
            <link>plugin://plugin.video.f4mTester/?url=http://portal.geniptv.com:8080/live/7hMtyUkelT/NOIhI9yvkL/7786.ts&amp;streamtype=TSDOWNLOADER&amp;name=</link> 
        </item> 
          <item> 
            <title>Fox Sports 2 FHD US</title> 
            <link>plugin://plugin.video.f4mTester/?url=#EXTINF:-1,Fox Sports&amp;streamtype=TSDOWNLOADER&amp;name=Fox Sports 2 FHD US</link> 
        </item> 
          <item> 
            <title></title> 
            <link>plugin://plugin.video.f4mTester/?url=http://portal.geniptv.com:8080/live/7hMtyUkelT/NOIhI9yvkL/554.ts&amp;streamtype=TSDOWNLOADER&amp;name=</link> 
        </item> 
          <item> 
            <title>Fox Sports 2 HD US</title> 
            <link>plugin://plugin.video.f4mTester/?url=#EXTINF:-1,Fox Sports&amp;streamtype=TSDOWNLOADER&amp;name=Fox Sports 2 HD US</link> 
        </item> 
          <item> 
            <title></title> 
            <link>plugin://plugin.video.f4mTester/?url=http://portal.geniptv.com:8080/live/7hMtyUkelT/NOIhI9yvkL/7759.ts&amp;streamtype=TSDOWNLOADER&amp;name=</link> 
        </item> 
          <item> 
            <title>Fox Sports 506 HD US</title> 
            <link>plugin://plugin.video.f4mTester/?url=#EXTINF:-1,Fox Sports&amp;streamtype=TSDOWNLOADER&amp;name=Fox Sports 506 HD US</link> 
        </item> 
          <item> 
            <title></title> 
            <link>plugin://plugin.video.f4mTester/?url=http://portal.geniptv.com:8080/live/7hMtyUkelT/NOIhI9yvkL/571.ts&amp;streamtype=TSDOWNLOADER&amp;name=</link> 
        </item> 
          <item> 
            <title>Fox Sports Arizona HD US</title> 
            <link>plugin://plugin.video.f4mTester/?url=#EXTINF:-1,Fox Sports&amp;streamtype=TSDOWNLOADER&amp;name=Fox Sports Arizona HD US</link> 
        </item> 
          <item> 
            <title></title> 
            <link>plugin://plugin.video.f4mTester/?url=http://portal.geniptv.com:8080/live/7hMtyUkelT/NOIhI9yvkL/7758.ts&amp;streamtype=TSDOWNLOADER&amp;name=</link> 
        </item> 
          <item> 
            <title>Fox Sports College Central HD US</title> 
            <link>plugin://plugin.video.f4mTester/?url=#EXTINF:-1,Fox Sports&amp;streamtype=TSDOWNLOADER&amp;name=Fox Sports College Central HD US</link> 
        </item> 
          <item> 
            <title></title> 
            <link>plugin://plugin.video.f4mTester/?url=http://portal.geniptv.com:8080/live/7hMtyUkelT/NOIhI9yvkL/7756.ts&amp;streamtype=TSDOWNLOADER&amp;name=</link> 
        </item> 
          <item> 
            <title>Fox Sports Florida HD US</title> 
            <link>plugin://plugin.video.f4mTester/?url=#EXTINF:-1,Fox Sports&amp;streamtype=TSDOWNLOADER&amp;name=Fox Sports Florida HD US</link> 
        </item> 
          <item> 
            <title></title> 
            <link>plugin://plugin.video.f4mTester/?url=http://portal.geniptv.com:8080/live/7hMtyUkelT/NOIhI9yvkL/7757.ts&amp;streamtype=TSDOWNLOADER&amp;name=</link> 
        </item> 
          <item> 
            <title>Fox Sports HD US</title> 
            <link>plugin://plugin.video.f4mTester/?url=#EXTINF:-1,Fox Sports&amp;streamtype=TSDOWNLOADER&amp;name=Fox Sports HD US</link> 
        </item> 
          <item> 
            <title></title> 
            <link>plugin://plugin.video.f4mTester/?url=http://portal.geniptv.com:8080/live/7hMtyUkelT/NOIhI9yvkL/7760.ts&amp;streamtype=TSDOWNLOADER&amp;name=</link> 
        </item> 
          <item> 
            <title>Fox Sports Net HD US</title> 
            <link>plugin://plugin.video.f4mTester/?url=#EXTINF:-1,Fox Sports&amp;streamtype=TSDOWNLOADER&amp;name=Fox Sports Net HD US</link> 
        </item> 
          <item> 
            <title></title> 
            <link>plugin://plugin.video.f4mTester/?url=http://portal.geniptv.com:8080/live/7hMtyUkelT/NOIhI9yvkL/7719.ts&amp;streamtype=TSDOWNLOADER&amp;name=</link> 
        </item> 
          <item> 
            <title>Fox Sports North HD US</title> 
            <link>plugin://plugin.video.f4mTester/?url=#EXTINF:-1,Fox Sports&amp;streamtype=TSDOWNLOADER&amp;name=Fox Sports North HD US</link> 
        </item> 
          <item> 
            <title></title> 
            <link>plugin://plugin.video.f4mTester/?url=http://portal.geniptv.com:8080/live/7hMtyUkelT/NOIhI9yvkL/7752.ts&amp;streamtype=TSDOWNLOADER&amp;name=</link> 
        </item> 
          <item> 
            <title>Fox Sports Prime Ticket 1 HD US</title> 
            <link>plugin://plugin.video.f4mTester/?url=#EXTINF:-1,Fox Sports&amp;streamtype=TSDOWNLOADER&amp;name=Fox Sports Prime Ticket 1 HD US</link> 
        </item> 
          <item> 
            <title></title> 
            <link>plugin://plugin.video.f4mTester/?url=http://portal.geniptv.com:8080/live/7hMtyUkelT/NOIhI9yvkL/7755.ts&amp;streamtype=TSDOWNLOADER&amp;name=</link> 
        </item> 
          <item> 
            <title>Fox Sports Prime Ticket Clippers HD US</title> 
            <link>plugin://plugin.video.f4mTester/?url=#EXTINF:-1,Fox Sports&amp;streamtype=TSDOWNLOADER&amp;name=Fox Sports Prime Ticket Clippers HD US</link> 
        </item> 
          <item> 
            <title></title> 
            <link>plugin://plugin.video.f4mTester/?url=http://portal.geniptv.com:8080/live/7hMtyUkelT/NOIhI9yvkL/7754.ts&amp;streamtype=TSDOWNLOADER&amp;name=</link> 
        </item> 
          <item> 
            <title>Fox Sports South HD US</title> 
            <link>plugin://plugin.video.f4mTester/?url=#EXTINF:-1,Fox Sports&amp;streamtype=TSDOWNLOADER&amp;name=Fox Sports South HD US</link> 
        </item> 
          <item> 
            <title></title> 
            <link>plugin://plugin.video.f4mTester/?url=http://portal.geniptv.com:8080/live/7hMtyUkelT/NOIhI9yvkL/7753.ts&amp;streamtype=TSDOWNLOADER&amp;name=</link> 
        </item> 
          <item> 
            <title>Free Form HD US</title> 
            <link>plugin://plugin.video.f4mTester/?url=http://portal.geniptv.com:8080/live/7hMtyUkelT/NOIhI9yvkL/572.ts&amp;streamtype=TSDOWNLOADER&amp;name=Free Form HD US</link> 
        </item> 
          <item> 
            <title>FreeForm FHD US</title> 
            <link>plugin://plugin.video.f4mTester/?url=http://portal.geniptv.com:8080/live/7hMtyUkelT/NOIhI9yvkL/7570.ts&amp;streamtype=TSDOWNLOADER&amp;name=FreeForm FHD US</link> 
        </item> 
          <item> 
            <title>FreeForm HD US</title> 
            <link>plugin://plugin.video.f4mTester/?url=http://portal.geniptv.com:8080/live/7hMtyUkelT/NOIhI9yvkL/7688.ts&amp;streamtype=TSDOWNLOADER&amp;name=FreeForm HD US</link> 
        </item> 
          <item> 
            <title>Fuel HD US</title> 
            <link>plugin://plugin.video.f4mTester/?url=http://portal.geniptv.com:8080/live/7hMtyUkelT/NOIhI9yvkL/496.ts&amp;streamtype=TSDOWNLOADER&amp;name=Fuel HD US</link> 
        </item> 
          <item> 
            <title>GSN HD US</title> 
            <link>plugin://plugin.video.f4mTester/?url=http://portal.geniptv.com:8080/live/7hMtyUkelT/NOIhI9yvkL/7749.ts&amp;streamtype=TSDOWNLOADER&amp;name=GSN HD US</link> 
        </item> 
          <item> 
            <title>Gol TV HD US</title> 
            <link>plugin://plugin.video.f4mTester/?url=http://portal.geniptv.com:8080/live/7hMtyUkelT/NOIhI9yvkL/7720.ts&amp;streamtype=TSDOWNLOADER&amp;name=Gol TV HD US</link> 
        </item> 
          <item> 
            <title>H2 US</title> 
            <link>plugin://plugin.video.f4mTester/?url=http://portal.geniptv.com:8080/live/7hMtyUkelT/NOIhI9yvkL/514.ts&amp;streamtype=TSDOWNLOADER&amp;name=H2 US</link> 
        </item> 
          <item> 
            <title>HBO Cinema HD US</title> 
            <link>plugin://plugin.video.f4mTester/?url=http://portal.geniptv.com:8080/live/7hMtyUkelT/NOIhI9yvkL/7712.ts&amp;streamtype=TSDOWNLOADER&amp;name=HBO Cinema HD US</link> 
        </item> 
          <item> 
            <title>HBO Comedy HD US</title> 
            <link>plugin://plugin.video.f4mTester/?url=http://portal.geniptv.com:8080/live/7hMtyUkelT/NOIhI9yvkL/530.ts&amp;streamtype=TSDOWNLOADER&amp;name=HBO Comedy HD US</link> 
        </item> 
          <item> 
            <title>HBO East US</title> 
            <link>plugin://plugin.video.f4mTester/?url=http://portal.geniptv.com:8080/live/7hMtyUkelT/NOIhI9yvkL/483.ts&amp;streamtype=TSDOWNLOADER&amp;name=HBO East US</link> 
        </item> 
          <item> 
            <title>HBO Family HD US</title> 
            <link>plugin://plugin.video.f4mTester/?url=http://portal.geniptv.com:8080/live/7hMtyUkelT/NOIhI9yvkL/7748.ts&amp;streamtype=TSDOWNLOADER&amp;name=HBO Family HD US</link> 
        </item> 
          <item> 
            <title>HBO HD US</title> 
            <link>plugin://plugin.video.f4mTester/?url=http://portal.geniptv.com:8080/live/7hMtyUkelT/NOIhI9yvkL/531.ts&amp;streamtype=TSDOWNLOADER&amp;name=HBO HD US</link> 
        </item> 
          <item> 
            <title>HBO Signature HD US</title> 
            <link>plugin://plugin.video.f4mTester/?url=http://portal.geniptv.com:8080/live/7hMtyUkelT/NOIhI9yvkL/7747.ts&amp;streamtype=TSDOWNLOADER&amp;name=HBO Signature HD US</link> 
        </item> 
          <item> 
            <title>HBO Signature US</title> 
            <link>plugin://plugin.video.f4mTester/?url=http://portal.geniptv.com:8080/live/7hMtyUkelT/NOIhI9yvkL/484.ts&amp;streamtype=TSDOWNLOADER&amp;name=HBO Signature US</link> 
        </item> 
          <item> 
            <title>HBO US</title> 
            <link>plugin://plugin.video.f4mTester/?url=http://portal.geniptv.com:8080/live/7hMtyUkelT/NOIhI9yvkL/7776.ts&amp;streamtype=TSDOWNLOADER&amp;name=HBO US</link> 
        </item> 
          <item> 
            <title>HBO Zone US</title> 
            <link>plugin://plugin.video.f4mTester/?url=http://portal.geniptv.com:8080/live/7hMtyUkelT/NOIhI9yvkL/532.ts&amp;streamtype=TSDOWNLOADER&amp;name=HBO Zone US</link> 
        </item> 
          <item> 
            <title>HGTV CA FHD US</title> 
            <link>plugin://plugin.video.f4mTester/?url=http://portal.geniptv.com:8080/live/7hMtyUkelT/NOIhI9yvkL/7566.ts&amp;streamtype=TSDOWNLOADER&amp;name=HGTV CA FHD US</link> 
        </item> 
          <item> 
            <title>HGTV FHD US</title> 
            <link>plugin://plugin.video.f4mTester/?url=http://portal.geniptv.com:8080/live/7hMtyUkelT/NOIhI9yvkL/7565.ts&amp;streamtype=TSDOWNLOADER&amp;name=HGTV FHD US</link> 
        </item> 
          <item> 
            <title>HGTV HD US</title> 
            <link>plugin://plugin.video.f4mTester/?url=http://portal.geniptv.com:8080/live/7hMtyUkelT/NOIhI9yvkL/495.ts&amp;streamtype=TSDOWNLOADER&amp;name=HGTV HD US</link> 
        </item> 
          <item> 
            <title>HGTV US</title> 
            <link>plugin://plugin.video.f4mTester/?url=http://portal.geniptv.com:8080/live/7hMtyUkelT/NOIhI9yvkL/7782.ts&amp;streamtype=TSDOWNLOADER&amp;name=HGTV US</link> 
        </item> 
          <item> 
            <title>HIFI US</title> 
            <link>plugin://plugin.video.f4mTester/?url=http://portal.geniptv.com:8080/live/7hMtyUkelT/NOIhI9yvkL/516.ts&amp;streamtype=TSDOWNLOADER&amp;name=HIFI US</link> 
        </item> 
          <item> 
            <title>HLN HD US</title> 
            <link>plugin://plugin.video.f4mTester/?url=http://portal.geniptv.com:8080/live/7hMtyUkelT/NOIhI9yvkL/7711.ts&amp;streamtype=TSDOWNLOADER&amp;name=HLN HD US</link> 
        </item> 
          <item> 
            <title>HSN YT LIVE 1080P HD US</title> 
            <link>plugin://plugin.video.f4mTester/?url=http://portal.geniptv.com:8080/live/7hMtyUkelT/NOIhI9yvkL/488.ts&amp;streamtype=TSDOWNLOADER&amp;name=HSN YT LIVE 1080P HD US</link> 
        </item> 
          <item> 
            <title>Hallmark Channel FHD US</title> 
            <link>plugin://plugin.video.f4mTester/?url=http://portal.geniptv.com:8080/live/7hMtyUkelT/NOIhI9yvkL/7567.ts&amp;streamtype=TSDOWNLOADER&amp;name=Hallmark Channel FHD US</link> 
        </item> 
          <item> 
            <title>Hallmark Channel HD US</title> 
            <link>plugin://plugin.video.f4mTester/?url=http://portal.geniptv.com:8080/live/7hMtyUkelT/NOIhI9yvkL/7746.ts&amp;streamtype=TSDOWNLOADER&amp;name=Hallmark Channel HD US</link> 
        </item> 
          <item> 
            <title>Hallmark Movies &amp; Mysteries HD US</title> 
            <link>plugin://plugin.video.f4mTester/?url=http://portal.geniptv.com:8080/live/7hMtyUkelT/NOIhI9yvkL/7713.ts&amp;streamtype=TSDOWNLOADER&amp;name=Hallmark Movies &amp; Mysteries HD US</link> 
        </item> 
          <item> 
            <title>Hallmark US</title> 
            <link>plugin://plugin.video.f4mTester/?url=http://portal.geniptv.com:8080/live/7hMtyUkelT/NOIhI9yvkL/515.ts&amp;streamtype=TSDOWNLOADER&amp;name=Hallmark US</link> 
        </item> 
          <item> 
            <title>History FHD US</title> 
            <link>plugin://plugin.video.f4mTester/?url=http://portal.geniptv.com:8080/live/7hMtyUkelT/NOIhI9yvkL/7564.ts&amp;streamtype=TSDOWNLOADER&amp;name=History FHD US</link> 
        </item> 
          <item> 
            <title>History HD US</title> 
            <link>plugin://plugin.video.f4mTester/?url=http://portal.geniptv.com:8080/live/7hMtyUkelT/NOIhI9yvkL/546.ts&amp;streamtype=TSDOWNLOADER&amp;name=History HD US</link> 
        </item> 
          <item> 
            <title>History US</title> 
            <link>plugin://plugin.video.f4mTester/?url=http://portal.geniptv.com:8080/live/7hMtyUkelT/NOIhI9yvkL/7781.ts&amp;streamtype=TSDOWNLOADER&amp;name=History US</link> 
        </item> 
          <item> 
            <title>ID Extra HD US</title> 
            <link>plugin://plugin.video.f4mTester/?url=http://portal.geniptv.com:8080/live/7hMtyUkelT/NOIhI9yvkL/7690.ts&amp;streamtype=TSDOWNLOADER&amp;name=ID Extra HD US</link> 
        </item> 
          <item> 
            <title>ID FHD US</title> 
            <link>plugin://plugin.video.f4mTester/?url=http://portal.geniptv.com:8080/live/7hMtyUkelT/NOIhI9yvkL/7563.ts&amp;streamtype=TSDOWNLOADER&amp;name=ID FHD US</link> 
        </item> 
          <item> 
            <title>IFC HD US</title> 
            <link>plugin://plugin.video.f4mTester/?url=http://portal.geniptv.com:8080/live/7hMtyUkelT/NOIhI9yvkL/7710.ts&amp;streamtype=TSDOWNLOADER&amp;name=IFC HD US</link> 
        </item> 
          <item> 
            <title>Investigation Discovery HD US</title> 
            <link>plugin://plugin.video.f4mTester/?url=http://portal.geniptv.com:8080/live/7hMtyUkelT/NOIhI9yvkL/7693.ts&amp;streamtype=TSDOWNLOADER&amp;name=Investigation Discovery HD US</link> 
        </item> 
          <item> 
            <title>Lifetime HD US</title> 
            <link>plugin://plugin.video.f4mTester/?url=http://portal.geniptv.com:8080/live/7hMtyUkelT/NOIhI9yvkL/7745.ts&amp;streamtype=TSDOWNLOADER&amp;name=Lifetime HD US</link> 
        </item> 
          <item> 
            <title>Longhorn Network HD US</title> 
            <link>plugin://plugin.video.f4mTester/?url=http://portal.geniptv.com:8080/live/7hMtyUkelT/NOIhI9yvkL/7709.ts&amp;streamtype=TSDOWNLOADER&amp;name=Longhorn Network HD US</link> 
        </item> 
          <item> 
            <title>MLB HD US</title> 
            <link>plugin://plugin.video.f4mTester/?url=http://portal.geniptv.com:8080/live/7hMtyUkelT/NOIhI9yvkL/573.ts&amp;streamtype=TSDOWNLOADER&amp;name=MLB HD US</link> 
        </item> 
          <item> 
            <title>MLB Network FHD US</title> 
            <link>plugin://plugin.video.f4mTester/?url=http://portal.geniptv.com:8080/live/7hMtyUkelT/NOIhI9yvkL/7562.ts&amp;streamtype=TSDOWNLOADER&amp;name=MLB Network FHD US</link> 
        </item> 
          <item> 
            <title>MLB Network HD US</title> 
            <link>plugin://plugin.video.f4mTester/?url=http://portal.geniptv.com:8080/live/7hMtyUkelT/NOIhI9yvkL/7701.ts&amp;streamtype=TSDOWNLOADER&amp;name=MLB Network HD US</link> 
        </item> 
          <item> 
            <title>MLB Network US</title> 
            <link>plugin://plugin.video.f4mTester/?url=http://portal.geniptv.com:8080/live/7hMtyUkelT/NOIhI9yvkL/574.ts&amp;streamtype=TSDOWNLOADER&amp;name=MLB Network US</link> 
        </item> 
          <item> 
            <title>MLB Strikeout HD US</title> 
            <link>plugin://plugin.video.f4mTester/?url=http://portal.geniptv.com:8080/live/7hMtyUkelT/NOIhI9yvkL/7700.ts&amp;streamtype=TSDOWNLOADER&amp;name=MLB Strikeout HD US</link> 
        </item> 
          <item> 
            <title>MSNBC FHD US</title> 
            <link>plugin://plugin.video.f4mTester/?url=http://portal.geniptv.com:8080/live/7hMtyUkelT/NOIhI9yvkL/7561.ts&amp;streamtype=TSDOWNLOADER&amp;name=MSNBC FHD US</link> 
        </item> 
          <item> 
            <title>MSNBC HD US</title> 
            <link>plugin://plugin.video.f4mTester/?url=http://portal.geniptv.com:8080/live/7hMtyUkelT/NOIhI9yvkL/575.ts&amp;streamtype=TSDOWNLOADER&amp;name=MSNBC HD US</link> 
        </item> 
          <item> 
            <title>MTV Base HD US</title> 
            <link>plugin://plugin.video.f4mTester/?url=http://portal.geniptv.com:8080/live/7hMtyUkelT/NOIhI9yvkL/7744.ts&amp;streamtype=TSDOWNLOADER&amp;name=MTV Base HD US</link> 
        </item> 
          <item> 
            <title>MTV FHD US</title> 
            <link>plugin://plugin.video.f4mTester/?url=http://portal.geniptv.com:8080/live/7hMtyUkelT/NOIhI9yvkL/7560.ts&amp;streamtype=TSDOWNLOADER&amp;name=MTV FHD US</link> 
        </item> 
          <item> 
            <title>MTV Rocks US</title> 
            <link>plugin://plugin.video.f4mTester/?url=http://portal.geniptv.com:8080/live/7hMtyUkelT/NOIhI9yvkL/494.ts&amp;streamtype=TSDOWNLOADER&amp;name=MTV Rocks US</link> 
        </item> 
          <item> 
            <title>NBA HD US</title> 
            <link>plugin://plugin.video.f4mTester/?url=http://portal.geniptv.com:8080/live/7hMtyUkelT/NOIhI9yvkL/533.ts&amp;streamtype=TSDOWNLOADER&amp;name=NBA HD US</link> 
        </item> 
          <item> 
            <title>NBA TV FHD US</title> 
            <link>plugin://plugin.video.f4mTester/?url=http://portal.geniptv.com:8080/live/7hMtyUkelT/NOIhI9yvkL/7559.ts&amp;streamtype=TSDOWNLOADER&amp;name=NBA TV FHD US</link> 
        </item> 
          <item> 
            <title>NBC FHD US</title> 
            <link>plugin://plugin.video.f4mTester/?url=http://portal.geniptv.com:8080/live/7hMtyUkelT/NOIhI9yvkL/7557.ts&amp;streamtype=TSDOWNLOADER&amp;name=NBC FHD US</link> 
        </item> 
          <item> 
            <title>NBC Golf Channel FHD US</title> 
            <link>plugin://plugin.video.f4mTester/?url=http://portal.geniptv.com:8080/live/7hMtyUkelT/NOIhI9yvkL/6147.ts&amp;streamtype=TSDOWNLOADER&amp;name=NBC Golf Channel FHD US</link> 
        </item> 
          <item> 
            <title>NBC Golf Channel HD US</title> 
            <link>plugin://plugin.video.f4mTester/?url=http://portal.geniptv.com:8080/live/7hMtyUkelT/NOIhI9yvkL/6146.ts&amp;streamtype=TSDOWNLOADER&amp;name=NBC Golf Channel HD US</link> 
        </item> 
          <item> 
            <title>NBC Golf FHD US</title> 
            <link>plugin://plugin.video.f4mTester/?url=http://portal.geniptv.com:8080/live/7hMtyUkelT/NOIhI9yvkL/7558.ts&amp;streamtype=TSDOWNLOADER&amp;name=NBC Golf FHD US</link> 
        </item> 
          <item> 
            <title>NBC Golf HD US</title> 
            <link>plugin://plugin.video.f4mTester/?url=http://portal.geniptv.com:8080/live/7hMtyUkelT/NOIhI9yvkL/7743.ts&amp;streamtype=TSDOWNLOADER&amp;name=NBC Golf HD US</link> 
        </item> 
          <item> 
            <title>NBC News HD US</title> 
            <link>plugin://plugin.video.f4mTester/?url=http://portal.geniptv.com:8080/live/7hMtyUkelT/NOIhI9yvkL/7742.ts&amp;streamtype=TSDOWNLOADER&amp;name=NBC News HD US</link> 
        </item> 
          <item> 
            <title>NBC SN HD US</title> 
            <link>plugin://plugin.video.f4mTester/?url=http://portal.geniptv.com:8080/live/7hMtyUkelT/NOIhI9yvkL/7741.ts&amp;streamtype=TSDOWNLOADER&amp;name=NBC SN HD US</link> 
        </item> 
          <item> 
            <title>NBC Sports Network FHD US</title> 
            <link>plugin://plugin.video.f4mTester/?url=#EXTINF:-1,NBC Sports&amp;streamtype=TSDOWNLOADER&amp;name=NBC Sports Network FHD US</link> 
        </item> 
          <item> 
            <title></title> 
            <link>plugin://plugin.video.f4mTester/?url=http://portal.geniptv.com:8080/live/7hMtyUkelT/NOIhI9yvkL/7556.ts&amp;streamtype=TSDOWNLOADER&amp;name=</link> 
        </item> 
          <item> 
            <title>NBC US</title> 
            <link>plugin://plugin.video.f4mTester/?url=http://portal.geniptv.com:8080/live/7hMtyUkelT/NOIhI9yvkL/490.ts&amp;streamtype=TSDOWNLOADER&amp;name=NBC US</link> 
        </item> 
          <item> 
            <title>NBCSN HD US</title> 
            <link>plugin://plugin.video.f4mTester/?url=http://portal.geniptv.com:8080/live/7hMtyUkelT/NOIhI9yvkL/555.ts&amp;streamtype=TSDOWNLOADER&amp;name=NBCSN HD US</link> 
        </item> 
          <item> 
            <title>NFL Network 1 US</title> 
            <link>plugin://plugin.video.f4mTester/?url=http://portal.geniptv.com:8080/live/7hMtyUkelT/NOIhI9yvkL/504.ts&amp;streamtype=TSDOWNLOADER&amp;name=NFL Network 1 US</link> 
        </item> 
          <item> 
            <title>NFL Network 1080i US</title> 
            <link>plugin://plugin.video.f4mTester/?url=http://portal.geniptv.com:8080/live/7hMtyUkelT/NOIhI9yvkL/505.ts&amp;streamtype=TSDOWNLOADER&amp;name=NFL Network 1080i US</link> 
        </item> 
          <item> 
            <title>NFL Network FHD US</title> 
            <link>plugin://plugin.video.f4mTester/?url=http://portal.geniptv.com:8080/live/7hMtyUkelT/NOIhI9yvkL/7555.ts&amp;streamtype=TSDOWNLOADER&amp;name=NFL Network FHD US</link> 
        </item> 
          <item> 
            <title>NFL Network HD US</title> 
            <link>plugin://plugin.video.f4mTester/?url=http://portal.geniptv.com:8080/live/7hMtyUkelT/NOIhI9yvkL/556.ts&amp;streamtype=TSDOWNLOADER&amp;name=NFL Network HD US</link> 
        </item> 
          <item> 
            <title>NFL Network US</title> 
            <link>plugin://plugin.video.f4mTester/?url=http://portal.geniptv.com:8080/live/7hMtyUkelT/NOIhI9yvkL/7793.ts&amp;streamtype=TSDOWNLOADER&amp;name=NFL Network US</link> 
        </item> 
          <item> 
            <title>NFL Now HD US</title> 
            <link>plugin://plugin.video.f4mTester/?url=http://portal.geniptv.com:8080/live/7hMtyUkelT/NOIhI9yvkL/7773.ts&amp;streamtype=TSDOWNLOADER&amp;name=NFL Now HD US</link> 
        </item> 
          <item> 
            <title>NFL Redzone HD US</title> 
            <link>plugin://plugin.video.f4mTester/?url=http://portal.geniptv.com:8080/live/7hMtyUkelT/NOIhI9yvkL/7772.ts&amp;streamtype=TSDOWNLOADER&amp;name=NFL Redzone HD US</link> 
        </item> 
          <item> 
            <title>NHL Network FHD US</title> 
            <link>plugin://plugin.video.f4mTester/?url=http://portal.geniptv.com:8080/live/7hMtyUkelT/NOIhI9yvkL/7554.ts&amp;streamtype=TSDOWNLOADER&amp;name=NHL Network FHD US</link> 
        </item> 
          <item> 
            <title>NHL Network US</title> 
            <link>plugin://plugin.video.f4mTester/?url=http://portal.geniptv.com:8080/live/7hMtyUkelT/NOIhI9yvkL/576.ts&amp;streamtype=TSDOWNLOADER&amp;name=NHL Network US</link> 
        </item> 
          <item> 
            <title>Nat Geo Wild HD US</title> 
            <link>plugin://plugin.video.f4mTester/?url=http://portal.geniptv.com:8080/live/7hMtyUkelT/NOIhI9yvkL/7692.ts&amp;streamtype=TSDOWNLOADER&amp;name=Nat Geo Wild HD US</link> 
        </item> 
          <item> 
            <title>Nat Geographic HD US</title> 
            <link>plugin://plugin.video.f4mTester/?url=http://portal.geniptv.com:8080/live/7hMtyUkelT/NOIhI9yvkL/7691.ts&amp;streamtype=TSDOWNLOADER&amp;name=Nat Geographic HD US</link> 
        </item> 
          <item> 
            <title>National Geographic US</title> 
            <link>plugin://plugin.video.f4mTester/?url=http://portal.geniptv.com:8080/live/7hMtyUkelT/NOIhI9yvkL/517.ts&amp;streamtype=TSDOWNLOADER&amp;name=National Geographic US</link> 
        </item> 
          <item> 
            <title>Nick FHD US</title> 
            <link>plugin://plugin.video.f4mTester/?url=http://portal.geniptv.com:8080/live/7hMtyUkelT/NOIhI9yvkL/7553.ts&amp;streamtype=TSDOWNLOADER&amp;name=Nick FHD US</link> 
        </item> 
          <item> 
            <title>OWN FHD US</title> 
            <link>plugin://plugin.video.f4mTester/?url=http://portal.geniptv.com:8080/live/7hMtyUkelT/NOIhI9yvkL/7552.ts&amp;streamtype=TSDOWNLOADER&amp;name=OWN FHD US</link> 
        </item> 
          <item> 
            <title>Oprah Winfrey Network HD US</title> 
            <link>plugin://plugin.video.f4mTester/?url=http://portal.geniptv.com:8080/live/7hMtyUkelT/NOIhI9yvkL/7740.ts&amp;streamtype=TSDOWNLOADER&amp;name=Oprah Winfrey Network HD US</link> 
        </item> 
          <item> 
            <title>Outdoor Channel HD US</title> 
            <link>plugin://plugin.video.f4mTester/?url=http://portal.geniptv.com:8080/live/7hMtyUkelT/NOIhI9yvkL/493.ts&amp;streamtype=TSDOWNLOADER&amp;name=Outdoor Channel HD US</link> 
        </item> 
          <item> 
            <title>Oxygen HD US</title> 
            <link>plugin://plugin.video.f4mTester/?url=http://portal.geniptv.com:8080/live/7hMtyUkelT/NOIhI9yvkL/7708.ts&amp;streamtype=TSDOWNLOADER&amp;name=Oxygen HD US</link> 
        </item> 
          <item> 
            <title>PAC-12 Arizona US</title> 
            <link>plugin://plugin.video.f4mTester/?url=http://portal.geniptv.com:8080/live/7hMtyUkelT/NOIhI9yvkL/557.ts&amp;streamtype=TSDOWNLOADER&amp;name=PAC-12 Arizona US</link> 
        </item> 
          <item> 
            <title>PAC-12 Bay Area US</title> 
            <link>plugin://plugin.video.f4mTester/?url=http://portal.geniptv.com:8080/live/7hMtyUkelT/NOIhI9yvkL/558.ts&amp;streamtype=TSDOWNLOADER&amp;name=PAC-12 Bay Area US</link> 
        </item> 
          <item> 
            <title>PAC-12 Los Angeles FHD US</title> 
            <link>plugin://plugin.video.f4mTester/?url=http://portal.geniptv.com:8080/live/7hMtyUkelT/NOIhI9yvkL/559.ts&amp;streamtype=TSDOWNLOADER&amp;name=PAC-12 Los Angeles FHD US</link> 
        </item> 
          <item> 
            <title>PAC-12 Oregon FHD US</title> 
            <link>plugin://plugin.video.f4mTester/?url=http://portal.geniptv.com:8080/live/7hMtyUkelT/NOIhI9yvkL/560.ts&amp;streamtype=TSDOWNLOADER&amp;name=PAC-12 Oregon FHD US</link> 
        </item> 
          <item> 
            <title>PAC-12 Washington FHD US</title> 
            <link>plugin://plugin.video.f4mTester/?url=http://portal.geniptv.com:8080/live/7hMtyUkelT/NOIhI9yvkL/561.ts&amp;streamtype=TSDOWNLOADER&amp;name=PAC-12 Washington FHD US</link> 
        </item> 
          <item> 
            <title>PBS FHD US</title> 
            <link>plugin://plugin.video.f4mTester/?url=http://portal.geniptv.com:8080/live/7hMtyUkelT/NOIhI9yvkL/7551.ts&amp;streamtype=TSDOWNLOADER&amp;name=PBS FHD US</link> 
        </item> 
          <item> 
            <title>Reelz HD US</title> 
            <link>plugin://plugin.video.f4mTester/?url=http://portal.geniptv.com:8080/live/7hMtyUkelT/NOIhI9yvkL/7739.ts&amp;streamtype=TSDOWNLOADER&amp;name=Reelz HD US</link> 
        </item> 
          <item> 
            <title>SEC Network HD US</title> 
            <link>plugin://plugin.video.f4mTester/?url=http://portal.geniptv.com:8080/live/7hMtyUkelT/NOIhI9yvkL/7707.ts&amp;streamtype=TSDOWNLOADER&amp;name=SEC Network HD US</link> 
        </item> 
          <item> 
            <title>SYFY FHD US</title> 
            <link>plugin://plugin.video.f4mTester/?url=http://portal.geniptv.com:8080/live/7hMtyUkelT/NOIhI9yvkL/7549.ts&amp;streamtype=TSDOWNLOADER&amp;name=SYFY FHD US</link> 
        </item> 
          <item> 
            <title>Science HD US</title> 
            <link>plugin://plugin.video.f4mTester/?url=http://portal.geniptv.com:8080/live/7hMtyUkelT/NOIhI9yvkL/7738.ts&amp;streamtype=TSDOWNLOADER&amp;name=Science HD US</link> 
        </item> 
          <item> 
            <title>Showtime 2 HD US</title> 
            <link>plugin://plugin.video.f4mTester/?url=http://portal.geniptv.com:8080/live/7hMtyUkelT/NOIhI9yvkL/7737.ts&amp;streamtype=TSDOWNLOADER&amp;name=Showtime 2 HD US</link> 
        </item> 
          <item> 
            <title>Showtime 2 US</title> 
            <link>plugin://plugin.video.f4mTester/?url=http://portal.geniptv.com:8080/live/7hMtyUkelT/NOIhI9yvkL/534.ts&amp;streamtype=TSDOWNLOADER&amp;name=Showtime 2 US</link> 
        </item> 
          <item> 
            <title>Showtime East HD US</title> 
            <link>plugin://plugin.video.f4mTester/?url=http://portal.geniptv.com:8080/live/7hMtyUkelT/NOIhI9yvkL/7736.ts&amp;streamtype=TSDOWNLOADER&amp;name=Showtime East HD US</link> 
        </item> 
          <item> 
            <title>Showtime FHD US</title> 
            <link>plugin://plugin.video.f4mTester/?url=http://portal.geniptv.com:8080/live/7hMtyUkelT/NOIhI9yvkL/535.ts&amp;streamtype=TSDOWNLOADER&amp;name=Showtime FHD US</link> 
        </item> 
          <item> 
            <title>Showtime Showcase HD US</title> 
            <link>plugin://plugin.video.f4mTester/?url=http://portal.geniptv.com:8080/live/7hMtyUkelT/NOIhI9yvkL/7735.ts&amp;streamtype=TSDOWNLOADER&amp;name=Showtime Showcase HD US</link> 
        </item> 
          <item> 
            <title>Showtime West US</title> 
            <link>plugin://plugin.video.f4mTester/?url=http://portal.geniptv.com:8080/live/7hMtyUkelT/NOIhI9yvkL/485.ts&amp;streamtype=TSDOWNLOADER&amp;name=Showtime West US</link> 
        </item> 
          <item> 
            <title>Smile Of A Child US</title> 
            <link>plugin://plugin.video.f4mTester/?url=http://portal.geniptv.com:8080/live/7hMtyUkelT/NOIhI9yvkL/492.ts&amp;streamtype=TSDOWNLOADER&amp;name=Smile Of A Child US</link> 
        </item> 
          <item> 
            <title>Spike HD US</title> 
            <link>plugin://plugin.video.f4mTester/?url=http://portal.geniptv.com:8080/live/7hMtyUkelT/NOIhI9yvkL/518.ts&amp;streamtype=TSDOWNLOADER&amp;name=Spike HD US</link> 
        </item> 
          <item> 
            <title>Spike TV HD US</title> 
            <link>plugin://plugin.video.f4mTester/?url=http://portal.geniptv.com:8080/live/7hMtyUkelT/NOIhI9yvkL/7727.ts&amp;streamtype=TSDOWNLOADER&amp;name=Spike TV HD US</link> 
        </item> 
          <item> 
            <title>Sportsnet East HD US</title> 
            <link>plugin://plugin.video.f4mTester/?url=#EXTINF:-1,Sports&amp;streamtype=TSDOWNLOADER&amp;name=Sportsnet East HD US</link> 
        </item> 
          <item> 
            <title></title> 
            <link>plugin://plugin.video.f4mTester/?url=http://portal.geniptv.com:8080/live/7hMtyUkelT/NOIhI9yvkL/7734.ts&amp;streamtype=TSDOWNLOADER&amp;name=</link> 
        </item> 
          <item> 
            <title>Sportsnet Ontario HD US</title> 
            <link>plugin://plugin.video.f4mTester/?url=#EXTINF:-1,Sports&amp;streamtype=TSDOWNLOADER&amp;name=Sportsnet Ontario HD US</link> 
        </item> 
          <item> 
            <title></title> 
            <link>plugin://plugin.video.f4mTester/?url=http://portal.geniptv.com:8080/live/7hMtyUkelT/NOIhI9yvkL/7733.ts&amp;streamtype=TSDOWNLOADER&amp;name=</link> 
        </item> 
          <item> 
            <title>Sportsnet West HD US</title> 
            <link>plugin://plugin.video.f4mTester/?url=#EXTINF:-1,Sports&amp;streamtype=TSDOWNLOADER&amp;name=Sportsnet West HD US</link> 
        </item> 
          <item> 
            <title></title> 
            <link>plugin://plugin.video.f4mTester/?url=http://portal.geniptv.com:8080/live/7hMtyUkelT/NOIhI9yvkL/7732.ts&amp;streamtype=TSDOWNLOADER&amp;name=</link> 
        </item> 
          <item> 
            <title>Sprout World HD US</title> 
            <link>plugin://plugin.video.f4mTester/?url=http://portal.geniptv.com:8080/live/7hMtyUkelT/NOIhI9yvkL/7706.ts&amp;streamtype=TSDOWNLOADER&amp;name=Sprout World HD US</link> 
        </item> 
          <item> 
            <title>Starz Cinema US</title> 
            <link>plugin://plugin.video.f4mTester/?url=http://portal.geniptv.com:8080/live/7hMtyUkelT/NOIhI9yvkL/536.ts&amp;streamtype=TSDOWNLOADER&amp;name=Starz Cinema US</link> 
        </item> 
          <item> 
            <title>Starz Comedy US</title> 
            <link>plugin://plugin.video.f4mTester/?url=http://portal.geniptv.com:8080/live/7hMtyUkelT/NOIhI9yvkL/537.ts&amp;streamtype=TSDOWNLOADER&amp;name=Starz Comedy US</link> 
        </item> 
          <item> 
            <title>Starz Edge HD US</title> 
            <link>plugin://plugin.video.f4mTester/?url=http://portal.geniptv.com:8080/live/7hMtyUkelT/NOIhI9yvkL/519.ts&amp;streamtype=TSDOWNLOADER&amp;name=Starz Edge HD US</link> 
        </item> 
          <item> 
            <title>Starz Edge US</title> 
            <link>plugin://plugin.video.f4mTester/?url=http://portal.geniptv.com:8080/live/7hMtyUkelT/NOIhI9yvkL/7780.ts&amp;streamtype=TSDOWNLOADER&amp;name=Starz Edge US</link> 
        </item> 
          <item> 
            <title>Starz Encore HD US</title> 
            <link>plugin://plugin.video.f4mTester/?url=http://portal.geniptv.com:8080/live/7hMtyUkelT/NOIhI9yvkL/7731.ts&amp;streamtype=TSDOWNLOADER&amp;name=Starz Encore HD US</link> 
        </item> 
          <item> 
            <title>Starz Encore US</title> 
            <link>plugin://plugin.video.f4mTester/?url=http://portal.geniptv.com:8080/live/7hMtyUkelT/NOIhI9yvkL/538.ts&amp;streamtype=TSDOWNLOADER&amp;name=Starz Encore US</link> 
        </item> 
          <item> 
            <title>SyFy HD US</title> 
            <link>plugin://plugin.video.f4mTester/?url=http://portal.geniptv.com:8080/live/7hMtyUkelT/NOIhI9yvkL/548.ts&amp;streamtype=TSDOWNLOADER&amp;name=SyFy HD US</link> 
        </item> 
          <item> 
            <title>SyFy US</title> 
            <link>plugin://plugin.video.f4mTester/?url=http://portal.geniptv.com:8080/live/7hMtyUkelT/NOIhI9yvkL/7779.ts&amp;streamtype=TSDOWNLOADER&amp;name=SyFy US</link> 
        </item> 
          <item> 
            <title>TBS FHD US</title> 
            <link>plugin://plugin.video.f4mTester/?url=http://portal.geniptv.com:8080/live/7hMtyUkelT/NOIhI9yvkL/7548.ts&amp;streamtype=TSDOWNLOADER&amp;name=TBS FHD US</link> 
        </item> 
          <item> 
            <title>TBS HD US</title> 
            <link>plugin://plugin.video.f4mTester/?url=http://portal.geniptv.com:8080/live/7hMtyUkelT/NOIhI9yvkL/578.ts&amp;streamtype=TSDOWNLOADER&amp;name=TBS HD US</link> 
        </item> 
          <item> 
            <title>TBS US</title> 
            <link>plugin://plugin.video.f4mTester/?url=http://portal.geniptv.com:8080/live/7hMtyUkelT/NOIhI9yvkL/7775.ts&amp;streamtype=TSDOWNLOADER&amp;name=TBS US</link> 
        </item> 
          <item> 
            <title>TLC HD US</title> 
            <link>plugin://plugin.video.f4mTester/?url=http://portal.geniptv.com:8080/live/7hMtyUkelT/NOIhI9yvkL/7730.ts&amp;streamtype=TSDOWNLOADER&amp;name=TLC HD US</link> 
        </item> 
          <item> 
            <title>TNT FHD US</title> 
            <link>plugin://plugin.video.f4mTester/?url=http://portal.geniptv.com:8080/live/7hMtyUkelT/NOIhI9yvkL/7547.ts&amp;streamtype=TSDOWNLOADER&amp;name=TNT FHD US</link> 
        </item> 
          <item> 
            <title>TNT HD US</title> 
            <link>plugin://plugin.video.f4mTester/?url=http://portal.geniptv.com:8080/live/7hMtyUkelT/NOIhI9yvkL/549.ts&amp;streamtype=TSDOWNLOADER&amp;name=TNT HD US</link> 
        </item> 
          <item> 
            <title>TSN 1 HD US</title> 
            <link>plugin://plugin.video.f4mTester/?url=http://portal.geniptv.com:8080/live/7hMtyUkelT/NOIhI9yvkL/579.ts&amp;streamtype=TSDOWNLOADER&amp;name=TSN 1 HD US</link> 
        </item> 
          <item> 
            <title>TSN 2 HD US</title> 
            <link>plugin://plugin.video.f4mTester/?url=http://portal.geniptv.com:8080/live/7hMtyUkelT/NOIhI9yvkL/580.ts&amp;streamtype=TSDOWNLOADER&amp;name=TSN 2 HD US</link> 
        </item> 
          <item> 
            <title>TSN 3 HD US</title> 
            <link>plugin://plugin.video.f4mTester/?url=http://portal.geniptv.com:8080/live/7hMtyUkelT/NOIhI9yvkL/581.ts&amp;streamtype=TSDOWNLOADER&amp;name=TSN 3 HD US</link> 
        </item> 
          <item> 
            <title>TSN 4 HD US</title> 
            <link>plugin://plugin.video.f4mTester/?url=http://portal.geniptv.com:8080/live/7hMtyUkelT/NOIhI9yvkL/582.ts&amp;streamtype=TSDOWNLOADER&amp;name=TSN 4 HD US</link> 
        </item> 
          <item> 
            <title>TSN 5 HD US</title> 
            <link>plugin://plugin.video.f4mTester/?url=http://portal.geniptv.com:8080/live/7hMtyUkelT/NOIhI9yvkL/583.ts&amp;streamtype=TSDOWNLOADER&amp;name=TSN 5 HD US</link> 
        </item> 
          <item> 
            <title>Travel Channel HD US</title> 
            <link>plugin://plugin.video.f4mTester/?url=http://portal.geniptv.com:8080/live/7hMtyUkelT/NOIhI9yvkL/7694.ts&amp;streamtype=TSDOWNLOADER&amp;name=Travel Channel HD US</link> 
        </item> 
          <item> 
            <title>UFC Fight Pass US</title> 
            <link>plugin://plugin.video.f4mTester/?url=http://portal.geniptv.com:8080/live/7hMtyUkelT/NOIhI9yvkL/6421.ts&amp;streamtype=TSDOWNLOADER&amp;name=UFC Fight Pass US</link> 
        </item> 
          <item> 
            <title>US Network HD US</title> 
            <link>plugin://plugin.video.f4mTester/?url=http://portal.geniptv.com:8080/live/7hMtyUkelT/NOIhI9yvkL/520.ts&amp;streamtype=TSDOWNLOADER&amp;name=US Network HD US</link> 
        </item> 
          <item> 
            <title>USA HD US</title> 
            <link>plugin://plugin.video.f4mTester/?url=http://portal.geniptv.com:8080/live/7hMtyUkelT/NOIhI9yvkL/7729.ts&amp;streamtype=TSDOWNLOADER&amp;name=USA HD US</link> 
        </item> 
          <item> 
            <title>USA Network FHD US</title> 
            <link>plugin://plugin.video.f4mTester/?url=http://portal.geniptv.com:8080/live/7hMtyUkelT/NOIhI9yvkL/7546.ts&amp;streamtype=TSDOWNLOADER&amp;name=USA Network FHD US</link> 
        </item> 
          <item> 
            <title>USA Network HD US</title> 
            <link>plugin://plugin.video.f4mTester/?url=http://portal.geniptv.com:8080/live/7hMtyUkelT/NOIhI9yvkL/547.ts&amp;streamtype=TSDOWNLOADER&amp;name=USA Network HD US</link> 
        </item> 
          <item> 
            <title>Univision HD US</title> 
            <link>plugin://plugin.video.f4mTester/?url=http://portal.geniptv.com:8080/live/7hMtyUkelT/NOIhI9yvkL/7704.ts&amp;streamtype=TSDOWNLOADER&amp;name=Univision HD US</link> 
        </item> 
          <item> 
            <title>Univision Miami HD US</title> 
            <link>plugin://plugin.video.f4mTester/?url=http://portal.geniptv.com:8080/live/7hMtyUkelT/NOIhI9yvkL/7703.ts&amp;streamtype=TSDOWNLOADER&amp;name=Univision Miami HD US</link> 
        </item> 
          <item> 
            <title>VH1 Classic US</title> 
            <link>plugin://plugin.video.f4mTester/?url=http://portal.geniptv.com:8080/live/7hMtyUkelT/NOIhI9yvkL/491.ts&amp;streamtype=TSDOWNLOADER&amp;name=VH1 Classic US</link> 
        </item> 
          <item> 
            <title>WWE HD US</title> 
            <link>plugin://plugin.video.f4mTester/?url=http://portal.geniptv.com:8080/live/7hMtyUkelT/NOIhI9yvkL/562.ts&amp;streamtype=TSDOWNLOADER&amp;name=WWE HD US</link> 
        </item> 
          <item> 
            <title>WWE Network FHD US</title> 
            <link>plugin://plugin.video.f4mTester/?url=http://portal.geniptv.com:8080/live/7hMtyUkelT/NOIhI9yvkL/7544.ts&amp;streamtype=TSDOWNLOADER&amp;name=WWE Network FHD US</link> 
        </item> 
          <item> 
            <title>WWE US</title> 
            <link>plugin://plugin.video.f4mTester/?url=http://portal.geniptv.com:8080/live/7hMtyUkelT/NOIhI9yvkL/7778.ts&amp;streamtype=TSDOWNLOADER&amp;name=WWE US</link> 
        </item> 
          <item> 
            <title>Willow FHD US</title> 
            <link>plugin://plugin.video.f4mTester/?url=http://portal.geniptv.com:8080/live/7hMtyUkelT/NOIhI9yvkL/7545.ts&amp;streamtype=TSDOWNLOADER&amp;name=Willow FHD US</link> 
        </item> 
          <item> 
            <title>YES Network FHD US</title> 
            <link>plugin://plugin.video.f4mTester/?url=http://portal.geniptv.com:8080/live/7hMtyUkelT/NOIhI9yvkL/7543.ts&amp;streamtype=TSDOWNLOADER&amp;name=YES Network FHD US</link> 
        </item> 
          <item> 
            <title>beINSports HD US</title> 
            <link>plugin://plugin.video.f4mTester/?url=#EXTINF:-1,beINSports&amp;streamtype=TSDOWNLOADER&amp;name=beINSports HD US</link> 
        </item> 
          <item> 
            <title></title> 
            <link>plugin://plugin.video.f4mTester/?url=http://portal.geniptv.com:8080/live/7hMtyUkelT/NOIhI9yvkL/506.ts&amp;streamtype=TSDOWNLOADER&amp;name=</link> 
        </item> 
          <item> 
            <title>truTV HD US</title> 
            <link>plugin://plugin.video.f4mTester/?url=http://portal.geniptv.com:8080/live/7hMtyUkelT/NOIhI9yvkL/7705.ts&amp;streamtype=TSDOWNLOADER&amp;name=truTV HD US</link> 
        </item> 
          <item> 
            <title>NBA Live 1 HD US</title> 
            <link>plugin://plugin.video.f4mTester/?url=http://portal.geniptv.com:8080/live/7hMtyUkelT/NOIhI9yvkL/8538.ts&amp;streamtype=TSDOWNLOADER&amp;name=NBA Live 1 HD US</link> 
        </item> 
          <item> 
            <title>NBA Live 2 HD US</title> 
            <link>plugin://plugin.video.f4mTester/?url=http://portal.geniptv.com:8080/live/7hMtyUkelT/NOIhI9yvkL/8537.ts&amp;streamtype=TSDOWNLOADER&amp;name=NBA Live 2 HD US</link> 
        </item> 
          <item> 
            <title>NBA Live 3 HD US</title> 
            <link>plugin://plugin.video.f4mTester/?url=http://portal.geniptv.com:8080/live/7hMtyUkelT/NOIhI9yvkL/8536.ts&amp;streamtype=TSDOWNLOADER&amp;name=NBA Live 3 HD US</link> 
        </item> 
          <item> 
            <title>NBA Live 4 HD US</title> 
            <link>plugin://plugin.video.f4mTester/?url=http://portal.geniptv.com:8080/live/7hMtyUkelT/NOIhI9yvkL/8535.ts&amp;streamtype=TSDOWNLOADER&amp;name=NBA Live 4 HD US</link> 
        </item> 
          <item> 
            <title>NBA Live 5 HD US</title> 
            <link>plugin://plugin.video.f4mTester/?url=http://portal.geniptv.com:8080/live/7hMtyUkelT/NOIhI9yvkL/8534.ts&amp;streamtype=TSDOWNLOADER&amp;name=NBA Live 5 HD US</link> 
        </item> 
          <item> 
            <title>NBA Live 6 HD US</title> 
            <link>plugin://plugin.video.f4mTester/?url=http://portal.geniptv.com:8080/live/7hMtyUkelT/NOIhI9yvkL/8533.ts&amp;streamtype=TSDOWNLOADER&amp;name=NBA Live 6 HD US</link> 
        </item> 
          <item> 
            <title>NBA Live 7 HD US</title> 
            <link>plugin://plugin.video.f4mTester/?url=http://portal.geniptv.com:8080/live/7hMtyUkelT/NOIhI9yvkL/8532.ts&amp;streamtype=TSDOWNLOADER&amp;name=NBA Live 7 HD US</link> 
        </item> 
          <item> 
            <title>NBA Live 8 HD US</title> 
            <link>plugin://plugin.video.f4mTester/?url=http://portal.geniptv.com:8080/live/7hMtyUkelT/NOIhI9yvkL/8531.ts&amp;streamtype=TSDOWNLOADER&amp;name=NBA Live 8 HD US</link> 
        </item> 
  